{"ana": "ana", "šarri": "šarru", "bēlīya": "bēlu", "urdaka": "ardu", "Aššur-šallimanni": "Aššur-šallimanni", "": "o[NA]NA", "lū": "lū", "šulmu": "šulmu", "madākte": "madaktu", "ša": "ša", "ina": "ina", "muhhi": "muhhu", "Armaya": "Armaya", "šarru": "šarru", "bēlī": "bēlu", "ṭēmu": "ṭēmu", "iškunaššīni": "šakānu", "mā": "mā", "nammeša": "namāšu", "likalka": "alāku", "issu": "ištu", "Maruri": "Maruru", "nissuhra": "sahāru", "libbi": "libbu", "Arimi": "Arumu", "pānīni": "pānu", "nissakan": "šakānu", "unqi": "unqu", "pūt": "pūtu", "Nippur": "Nippur", "muhhīni": "muhhu", "naṣūni": "našû", "muhhišunu": "muhhu", "illaka": "alāku", "puhra": "pahāru", "šeʾu": "šeʾu", "ubbulu": "ubbulu", "bētāti": "bītu", "Bit-Amukanni": "Bit-Amukanni", "usha": "nasāhu", "nissuhur": "sahāru", "kammusāni": "kamsu", "ša-pēthallāti": "ša-pēthalli", "ammar": "ammar", "nušētiqūni": "etēqu", "kammasūni": "kamsu", "ṣābāni": "ṣābu", "ālikūti": "āliku", "uṣabbitūni": "ṣabātu", "ūmi": "ūmu", "aktašāda": "kašādu", "lā": "lā", "ṭēnšunu": "ṭēmu", "assapra": "šapāru", "Aššur-leʾi": "Aššur-leʾi", "rab": "rabû", "šāqê": "šāqû", "bēt": "bīt", "issi": "išti", "emūqī": "emūqu", "ērubūni": "erēbu", "Ursa": "Ursa", "ittalka": "alāku", "iktašassu": "kašādu", "issēn": "ištēn", "libbišunu": "libbu", "ūṣīa": "aṣû", "illāka": "alāku", "bīrāti": "birtu", "išakkan": "šakānu", "qarābu": "qarābu", "eppaš": "epēšu", "kî": "kī", "ilaʾʾûni": "leʾû", "lēpuš": "epēšu", "adanniš": "adanniš", "nadabāki": "natbāku", "kurummāti": "kurummatu", "išpuranni": "šapāru", "maʾda": "mādu", "lūbilūni": "wabālu", "lidibuku": "tabāku", "Bel-duri": "Bel-duri", "issakan": "šakānu", "pāhāti": "pīhātu", "gabbu": "gabbu", "kusāpī": "kusāpu", "kissutu": "kissatu", "Šamaš-ahu-iddina": "Šamaš-ahu-iddina", "issikunu": "išti", "lintuhu": "matāhu", "Adad-isseʾa": "Adad-isseʾa", "Bel-lešir": "Bel-lešir", "Abu-lešir": "Abu-lešir", "lušākilu": "akālu", "immaggur": "magāru", "išammi": "šemû", "atâ": "atā", "innûte": "innû", "ālāni": "ālu", "madbar": "madbaru", "gabbišunu": "gabbu", "ahîši": "ahāmiš", "pannugu": "pannugu", "lišpura": "šapāru", "ālānišunu": "ālu", "lišṭuru": "šaṭāru", "aṣappu": "aṣappu", "Hamate": "Hamat", "issuhūni": "nasāhu", "anāku": "anāku", "anākūma": "anāku", "šû": "šū", "šunūma": "šunu", "šunu": "šunu", "šiāri": "šiāru", "idūkāni": "dâku", "ēpišūte": "ēpišu", "attunu": "attunu", "annīu": "annû", "urhi": "arhu", "mē": "meʾatu", "imārī": "imēru", "gimru": "gimru", "līmu": "līm", "zakkue": "zakkû", "Kummuhaya": "Kummuhaya", "bētu": "bītu", "ūda": "wadû", "mardiāte": "mardītu", "mardītu": "mardītu", "annīnu": "anīnu", "nimattāha": "matāhu", "šunāya": "šunāʾa", "imattuhu": "matāhu", "ūmâ": "ūma", "ibbalkutu": "nabalkutu", "annuri": "annûri", "ṣarpu": "ṣarpu", "uptahhir": "pahāru", "Ṣil-Bel": "Ṣil-Bel", "aktanak": "kanāku", "nišē": "nišu", "lurāme": "ramû", "bēti": "bītu", "ussuk": "esēhu", "qātē": "qātu", "Iba": "Iba", "ussēbila": "wabālu", "pān": "pānu", "abat": "awātu", "Inurta-belu-uṣur": "Inurta-belu-uṣur", "gammalī": "gammalu", "turtānu": "tartānu", "eddanakkanni": "tadānu", "ašur": "ašāru", "muhur": "mahāru", "Badiʾ-il": "Badiʾ-il", "pānīka": "pānu", "piqdaššu": "paqādu", "māti": "mātu", "liriʾû": "reʾû", "annurig": "annûri", "Arbaya": "Arbaya", "annūti": "annû", "ittahāṣa": "mahāṣu", "maṣṣartakunu": "maṣṣartu", "timāli": "timāli", "šalši-ūme": "šalšūmi", "mudabir": "madbaru", "dannat": "dannu", "yābilīkunu": "yābilu", "mudābiri": "madbaru", "mātī": "mātu", "uššura": "uššuru", "adu": "adi", "hūlu": "hūlu", "Tabalaya": "Tabalaya", "ušahkamūka": "hakāmu", "birte": "birti", "Niʾu": "Niʾu", "Qidisi": "Qadisu", "zarʾu": "zēru", "arišūni": "eršu", "galīti": "galītu", "tallakanni": "alāku", "Dimašqa": "Dimašqa", "illakūninni": "alāku", "Arantu": "Arantu", "šapārišunu": "šapāru", "kibāti": "kibtu", "aradka": "ardu", "Nabu-damiq": "Nabu-damiq", "dinān": "dinānu", "lullik": "alāku", "Nabu": "Nabu", "u": "u", "Marduk": "Marduk", "likrubu": "karābu", "ummā": "umma", "bēlīyāma": "bēlu", "lāmūwa": "ellāmu-", "dibbu": "dibbu", "ibtanû": "banû", "enna": "enna", "hanṭiš": "hamṭiš", "harrāna": "harrānu", "Nabu-bani": "Nabu-bani", "sīsê": "sisû", "lišpuramma": "šapāru", "batbatni": "battubattu", "Barsip": "Barsip", "lilliku": "alāku", "mār": "māru", "šipri": "šipru", "Yaqiri": "Yaqiru", "nasīku": "nasīku", "Liʾtamu": "Liʾtamu", "lillikamma": "alāku", "ṣābē": "ṣābu", "napulti": "napištu", "lidkâmma": "dekû", "Dilbat": "Dilbat", "lēlûni": "elû", "mindēma": "minde", "erēbi": "erēbu", "ibašši": "bašû", "ūdī": "wadû", "emūqu": "emūqu", "šapārīni": "šapāru", "ēdiš": "ēdiš", "Ašipa": "Ašipa", "išpurannīni": "šapāru", "unammišanni": "namāšu", "Kutiu": "Kute", "Sippar": "Sippar", "ētarba": "erēbu", "šittā": "šina", "ūmāti": "ūmu", "Babili": "Babili", "kammusāk": "kamsu", "qurbati": "qurbu", "aqrib": "qerēbu", "Mušezib-ilu": "Mušezib-ilu", "Kar-Aššur": "Kar-Aššur", "illikanni": "alāku", "eleppāti": "eleppu", "assadāda": "šadādu", "mardīti": "mardītu", "šapal": "šaplu", "Kute": "Kute", "attalak": "alāku", "ūm": "ūmu", "unammāša": "namāšu", "akarrar": "karāru", "Aššur-matka-tera": "Aššur-matka-tera", "maʾuttāti": "maʾʾuttu", "kannuša": "kannušu", "mahīru": "mahīru", "deʾiq": "damqu", "imāru": "imēru", "manê": "manû", "erî": "erû", "Ninua": "Ninua", "tallak": "alāku", "Halahhi": "Halahhu", "šāpti": "šīpātu", "altapra": "šapāru", "umma": "umma", "minamma": "minamma", "eppuš": "epēšu", "aqbû": "qabû", "Bel": "Bel", "iqtabi": "qabû", "šarrūtu": "šarrūtu", "iši": "našû", "pîya": "pû", "mannu": "mannu", "šalānūwa": "šalânū-", "inašši": "našû", "šarrūti": "šarrūtu", "išši": "našû", "mahrî": "mahrû", "ummânni": "ummiānu", "iqtabaššu": "qabû", "epuš": "epēšu", "iltapraššu": "šapāru", "ultu": "ištu", "sūnu": "sūnu", "āli": "ālu", "Nergal-ašared": "Nergal-ašared", "kāri": "kāru", "sissê": "sisû", "attahar": "mahāru", "attidin": "tadānu", "urdāni": "ardu", "udīni": "udīni", "rēhti": "rēhtu", "amahhar": "mahāru", "ālšunu": "ālu", "dannūti": "dannu", "nārti": "nārtu", "Wargi": "Wargi", "irtedûni": "redû", "dēktašunu": "dīktu", "lišʾal": "šâlu", "Qurdi-Aššur-lamur": "Qurdi-Aššur-lamur", "Ṣuraya": "Ṣurraya", "iqbûni": "qabû", "dibbī": "dibbu", "issīšu": "išti", "ṭāb": "ṭābu", "kārāni": "kāru", "rammûniššu": "rammû", "urdānīšu": "ardu", "karrāni": "kāru", "errubu": "erēbu", "uṣṣū": "aṣû", "iddunu": "tadānu", "imahharūni": "mahāru", "Labnana": "Labnana", "pānīšu": "pānu", "elliu": "elû", "urrudu": "arādu", "ēṣē": "iṣu", "ušerradūni": "arādu", "ušerradāni": "arādu", "miksīšu": "miksu", "amakkis": "makāsu", "mākisāni": "mākisu", "gabbi": "gabbu", "uptaqqīdi": "paqādu", "maṣṣartu": "maṣṣartu", "šadê": "šadû", "inaṣṣuru": "naṣāru", "mākisu": "mākisu", "Ṣiduni": "Ṣidunu", "uraddûninni": "redû", "aptiqīdi": "paqādu", "Ṣidunaya": "Ṣidunaya", "uktaššidūniššu": "kašādu", "harammāma": "haramma", "Ituʾaya": "Ituʾaya", "assapar": "šapāru", "ussagariru": "qarāru", "urkīte": "arkītu", "issaparūni": "šapāru", "ittaṣṣu": "našû", "ussēribu": "erēbu", "annīe": "annû", "aqṭibaššunu": "qabû", "nuk": "nuk", "šēridanni": "arādu", "dullakunu": "dullu", "epeša": "epēšu", "Muṣuraya": "Muṣuraya", "Palaštaya": "Pilistaya", "taddana": "tadānu", "ulamâ": "ullāman", "urammakkunu": "ramû", "tellia": "elû", "Kašpunaya": "Kašpunaya", "mīni": "mīnu", "tuharrīdi": "harādu", "taddinaššunu": "tadānu", "akī": "akī", "ēkalli": "ēkallu", "išapparūni": "šapāru", "aṣṣabta": "ṣabātu", "dullu": "dullu", "ētapaš": "epēšu", "kanīku": "kanīku", "illakni": "alāku", "ahhūr": "hurri", "ahī": "ahu", "ullue": "elû", "isītāte": "isītu", "attašha": "nasāhu", "abullumma": "abullu", "bētāni": "bītānu", "arṣip": "raṣāpu", "attiši": "našû", "urtammi": "ramû", "ṣāb": "ṣābu", "šarrišunu": "šarru", "uṣṣabbita": "ṣabātu", "issīya": "išti", "ittalkūni": "alāku", "ša-rēši": "ša-rēši", "bīrte": "birtu", "Šiʾanaya": "Šiʾanaya", "ussērib": "erēbu", "ipaṭṭarūšunu": "paṭāru", "Yasubaya": "Yasubayu", "Kašpuna": "Kašpuna", "šērib": "erēbu", "mê": "mû", "dannu": "dannu", "imarruṣu": "marāṣu", "kīma": "kīma", "mêšunu": "mû", "Immiu": "Immiu", "ittaškunu": "šakānu", "ušerrabšunu": "erēbu", "eleppānišunu": "eleppu", "nammiš": "namāšu", "ayāši": "yâšim", "unammišūni": "namāšu", "nakkira": "nakāru", "maṣṣartīya": "maṣṣartu", "qāni": "qannu", "laššu": "laššu", "Mazamuaya": "Mazamuaya", "Urzuhinaya": "Arzuhinaya", "sihirti": "sihirtu", "uṭṭātišunu": "uṭṭatu", "urammûni": "ramû", "imattahūni": "matāhu", "Ululayu": "Ululayu", "Mat-Aššur": "Mat-Aššur", "ēkurrāti": "ēkurru", "libbu": "libbu", "maqarrāti": "maqarrutu", "kuppê": "kupû", "qātāya": "qātā-", "nāri": "nāru", "attūrid": "arādu", "pānīya": "pānu", "ihtašlu": "hašālu", "ētaspu": "esēpu", "Ubru-Nergal": "Ubru-Nergal", "ša-qurbūti": "ša-qurbūti", "marʾe-Babili": "mar-Babili", "uṣṣabbit": "ṣabātu", "šipṭu": "šipṭu", "issakna": "šakānu", "iqṭibi": "qabû", "ahīya": "ahu", "Aplaya": "Aplaya", "Munnabittu": "Munnabitu", "Ṣalliya": "Ṣalliya", "La-basi": "La-basi", "Bel-ibni": "Bel-ibni", "Sulaya": "Sulaya", "Šuzubi": "Šuzubu", "Šamšati": "Šamšati", "Bel-šabši": "Bel-ušabši", "šumēli": "šumēlu", "adi": "adi", "kaqqari": "qaqqaru", "ittūar": "târu", "iqṭūlu": "qâlu", "Mukin-zeri": "Mukin-zeri", "Nabu-ahhe-šullim": "Nabu-ahhe-šullim", "hurāṣi": "hurāṣu", "naṣa": "našû", "šappu": "šappu", "akla": "kalû", "ukâl": "kullu", "siparri": "siparru", "issip": "esēpu", "aktalaššu": "kalû", "aqbûni": "qabû", "ettiqa": "etēqu", "allaka": "alāku", "Dummuqu": "Dummuqu", "Nergal": "Nergal", "Laṣ": "Laṣ", "ṭuppī": "ṭuppu", "ālu": "ālu", "ūmussu": "ūmussu", "mahar": "mahru", "akarrab": "karābu", "ittīšu": "itti", "īterub": "erēbu", "Babilaya": "Babilaya", "qereb": "qerbu", "mātīya": "mātu", "tapallaha": "palāhu", "ṣebû": "ṣabû", "ītelû": "elû", "mar": "ammar", "irtīya": "irtu", "illikūninni": "alāku", "šumātišunu": "šumu", "egerti": "egertu", "šuṭur": "šaṭāru", "šēbila": "wabālu", "menimmēni": "menimeni", "illika": "alāku", "šaniūte": "šanû", "piqid": "paqādu", "rēhūte": "rēhu", "piqīdi": "paqādu", "qēpu": "qīpu", "rāʾyu": "rēʾû", "pāhiti": "pīhātu", "dulli": "dullu", "addinaššūni": "tadānu", "birti": "birti", "ēnātīšu": "īnu", "untaddīdi": "madādu", "šaniu": "šanû", "dullāni": "dullu", "urtamme": "ramû", "Arrapha": "Arrapha", "ittalak": "alāku", "imitti": "imittu", "išapparanni": "šapāru", "memmēni": "memēni", "kutallīya": "kutallu", "lillika": "alāku", "lumaddidu": "madādu", "dullušu": "dullu", "Inurta-ilaʾi": "Inurta-ilaʾi", "maqtu": "maqtu", "pāniu": "pānû", "ušēbilūni": "wabālu", "iqṭibia": "qabû", "uktaššidūni": "kašādu", "qanni": "qannu", "ālīma": "ālu", "kallamāri": "kallâmāre", "matāhi": "matāhu", "dātuššunu": "dāt", "ušanṣiu": "maṣû", "ikšudūšunu": "kašādu", "ebūršunu": "ebūru", "nāgir": "nāgiru", "alpāni": "alpu", "Nergal-uballiṭ": "Nergal-uballiṭ", "šanie": "šanû", "annāka": "annaka", "liqbûniššunu": "qabû", "alpānišunu": "alpu", "lillikūni": "alāku", "ludurrisu": "darāsu", "lintūhu": "matāhu", "lušēribu": "erēbu", "ša-maṣṣarātišunu": "ša-maṣṣarti", "ebūri": "ebūru", "izzazzu": "izuzzu", "pānišunu": "pānu", "Duri-Aššur": "Duri-Aššur", "bētīka": "bītu", "ṣābānīya": "ṣābu", "ibaššûni": "bašû", "ušaṣbat": "ṣabātu", "ettiqūni": "etēqu", "illakūni": "alāku", "nakrūti": "nakru", "šēpē": "šēpu", "ammiti": "ammatu", "līriku": "arāku", "kadammē": "kadammu", "ša-daʾāni": "ša-danāni", "rappāni": "rappu", "teppašūni": "epēšu", "mugirri": "mugerru", "kabburu": "kubburu", "pānāt": "pānātu", "gupnī": "gupnu", "mahīṣi": "mahṣu", "šapla": "šaplu", "pūlāni": "pīlu", "mūruku": "mūraku", "tallakāti": "tallaktu", "ikarrarūni": "karāru", "basi": "basi", "šāru": "šāru", "qurbu": "qurbu", "qabsi": "qabaltu", "tašarrīme": "šarāmu", "kaqqaru": "qaqqaru", "irappiška": "rapāšu", "pūlu": "pīlu", "likruru": "karāru", "katammāti": "katammu", "teppaš": "epēšu", "massikī": "maštaku", "dullīka": "dullu", "ēpuš": "epēšu", "mišil": "mišlu", "dūri": "dūru", "tašakkan": "šakānu", "mišilma": "mišlu", "arkūti": "arku", "hurrātešu": "hurratu", "tumalla": "malû", "šupur": "šapāru", "tallakti": "tallaktu", "karrūni": "karru", "tušaʾʾāda": "âdu", "šerʾānī": "šerʾānu", "hannimma": "annû", "šaplê": "šaplû", "kubbiri": "kubburu", "mīnu": "mīnu", "Ambati": "Ambati", "pūtuhu": "pūtuhhu", "bīrti": "birtu", "išakkanūni": "šakānu", "kūmuššu": "kūm", "uššāba": "ašābu", "uššē": "uššu", "esīti": "asaʾītu", "adri": "adru", "ikrarūni": "karāru", "ugammerūni": "gamāru", "libittāti": "libittu", "riṣpa": "raṣāpu", "gammerašši": "gamāru", "tikpī": "tibku", "turakkāsa": "rakāsu", "tamlâ": "tamlīu", "rupšu": "rupšu", "pānīti": "pānītu", "uraddûni": "redû", "tamaddāda": "madādu", "mūlû": "mūlû", "šalhê": "šalhû", "Dahina": "Dahinu", "mazzalitīšu": "mazzaztu", "iddaggilu": "dagālu", "šalussu": "šalšu", "šattu": "šattu", "iššûni": "našû", "kapri": "kapru", "qēmē": "qēmu", "kūm": "kūm", "Guzana": "Guzana", "immerē": "immeru", "šappāti": "šapputu", "ussēbil": "wabālu", "ālummâ": "ālu", "ṣarpi": "ṣarpu", "laqi": "leqû", "ālû": "ālu", "aqarrib": "qerēbu", "pî": "pû", "hubtu": "hubtu", "Šamaš-bunaya": "Šamaš-bunaya", "ṭēme": "ṭēmu", "šunāšunu": "šunāšunu", "tušēbila": "wabālu", "Ituʾe": "Ituʾaya", "šiddi": "šiddu", "Diglat": "Diglat", "batti": "battu", "issišunu": "išti", "ittūṣiu": "aṣû", "ittalku": "alāku", "Ruʾu": "Ruʾuaya", "Kar-Šamaš": "Kar-Šamaš", "Amudani": "Amudanu", "mātišunu": "mātu", "ṣābānēnu": "ṣābu", "pānīte": "pānītu", "ūṣī": "aṣû", "dassu": "daltu", "tallīša": "tallu", "tattahaṣ": "mahāṣu", "nāgiru": "nāgiru", "šî": "šī", "tattūṣi": "aṣû", "isītu": "isītu", "kirie": "kirû", "tuntaggir": "mugguru", "ētabaš": "epēšu", "izzazūni": "izuzzu", "ētabru": "ebēru", "Šubriaya": "Šubriaya", "išpuraššu": "šapāru", "issapra": "šapāru", "annî": "annû", "assapraššu": "šapāru", "nūku": "nuk", "kutal": "kutallu", "tērišannīni": "erēšu", "ayāšimma": "yâšim", "šupra": "šapāru", "lallika": "alāku", "issurri": "issurri", "iqabbi": "qabû", "nakru": "nakru", "nakrumma": "nakru", "lāšu": "laššu", "ūtakkiš": "akāšu", "nāpassī": "nāpaltu", "lāmur": "amāru", "šumma": "šumma", "hannēša": "annîša", "mūši": "mūšu", "ša-šarri": "ša-šarri", "igarrûni": "gerû", "labīrti": "labīru", "Dayan-Adad": "Dayan-Adad", "marʾat": "mārtu", "Ubri": "Ubri", "nuārāti": "nārtu", "diqāru": "diqāru", "erû": "erû", "ammiu": "ammiu", "Marduk-naṣir": "Marduk-naṣir", "attannaššu": "tadānu", "Adda-hati": "Adda-hati", "šaknūte": "šaknu", "ālānāte": "ālu", "ussaddina": "tadānu", "bilāt": "biltu", "Gargamis": "Gargamis", "šiqlī": "šiqlu", "šaddīnī": "saddinu", "kitê": "kitû", "issēniš": "ištēniš", "šiprīya": "šipru", "iddinūni": "tadānu", "ittanna": "tadānu", "Dannaya": "Dannaya", "untaṭṭi": "maṭû", "dēkūni": "dīku", "šalmu": "šalmu", "utru": "atru", "Argite": "Argite", "Ṣupite": "Ṣupat", "lūbīli": "wabālu", "pānātuššunu": "pānātu", "zarʾē": "zēru", "eṣṣīdi": "eṣēdu", "Labaʾu": "Labaʾu", "Aššuraya": "Aššuraya", "liddina": "tadānu", "lušaṣabīti": "ṣabātu", "ša-muhhi-āli": "ša-muhhi-āli", "etê": "atû", "tillāni": "tīlu", "lūridūni": "arādu", "lirṣipu": "raṣāpu", "itturdūni": "arādu", "hannūte": "annû", "lūridūnê": "arādu", "iqabbûni": "qabû", "kayamānu": "kayyamānu", "girûtu": "girûtu", "ašīāṭa": "šâṭu", "ahâti": "ahû", "īriši": "erēšu", "uṭṭatu": "uṭṭatu", "ēriš": "erēšu", "inniṣidu": "eṣēdu", "maʾuttu": "maʾʾuttu", "Zeru-ibni": "Zeru-ibni", "illik": "alāku", "itti": "itti", "Ṣalam-šarri-iqbi": "Ṣalam-šarri-iqbi", "niqbû": "qabû", "ašābi": "ašābu", "alpu": "alpu", "tartānu": "tartānu", "issapāra": "šapāru", "šallutu": "šallatu", "pānikunu": "pānu", "Tutammu": "Tutammu", "ša-rēšānišu": "ša-rēši", "illakâ": "alāku", "takarrar": "karāru", "Abi-hari": "Abi-hari", "illakanni": "alāku", "liddinakka": "tadānu", "Ahunu": "Ahunu", "arhiš": "arhiš", "lizziz": "izuzzu", "harrāni": "harrānu", "iddaglu": "dagālu", "šazbussu": "šazbussu", "harrānu": "harrānu", "asahhura": "sahāru", "madādi": "madādu", "amahharšu": "mahāru", "rēš": "rēšu", "lišši": "našû", "Salama": "Salamu", "dināna": "dinānu", "amat": "awātu", "iqbû": "qabû", "adû": "adû", "šiprāni": "šipru", "mārē": "māru", "Puqudu": "Puqudu", "ītetqu": "etēqu", "iptû": "petû", "appāru": "appāru", "ṣilli": "ṣillu", "ittiq": "etēqu", "mimma": "mimma", "elēnūwa": "elēnu", "qāti": "qātu", "šinīšu": "šinīšu", "Hallusu": "Hallusu", "Nabu-kenu-uṣur": "Nabu-kenu-uṣur", "pāhutu": "pīhātu", "Tilleya": "Tille", "ussahaliqūšunu": "halāqu", "Upume": "Upumu", "ittaṣṣūšunu": "našû", "ašʾalūni": "šâlu", "uṣṣiṣūni": "uṣṣuṣu", "rādiu": "rādiu", "irtidanni": "redû", "Šubria": "Šubria", "harrānšu": "harrānu", "iškunūni": "šakānu", "aṣṣabat": "ṣabātu", "rādi": "rādiu", "kibsi": "kibsu", "attidīni": "tadānu", "mūku": "muk", "alik": "alāku", "amur": "amru", "pitti": "pitti", "laqabi": "qabû", "ulâ": "ūla", "lubaʾʾišu": "buʾʾû", "uptazzīri": "pazāru", "amēlumma": "awīlu", "urdu": "ardu", "ētatqa": "etēqu", "amēli": "awīlu", "naṣāka": "našû", "kūdunu": "kūdanu", "tattanna": "tadānu", "iddan": "tadānu", "ušahaliqūšūni": "halāqu", "bēl": "bēlu", "ṭābtišunu": "ṭābtu", "ussēbilaššu": "wabālu", "lišʾalšu": "šâlu", "muhhīka": "muhhu", "mate": "mati", "tamattāha": "matāhu", "amtatha": "matāhu", "pāniūte": "pānû", "amattāha": "matāhu", "ṭuppi": "ṭuppu", "ṭupšar": "ṭupšarru", "nišēšunu": "nišu", "Puqudaya": "Puqudaya", "lūbilūniššunu": "wabālu", "nupšāti": "napištu", "ūme": "ūmu", "Kalhi": "Kalhu", "ušaddanšunu": "tadānu", "limnūšunu": "manû", "nišēšunūni": "nišu", "lūbilu": "wabālu", "lipqidu": "paqādu", "Barhalzi": "Barhalza", "šūtu": "šūtu", "ubbalūniššu": "wabālu", "assaprakka": "šapāru", "Nabu-balassu-iqbi": "Nabu-balassu-iqbi", "šulmi": "šulmu", "aššu": "aššu", "akanni": "akanni", "ul": "ul", "illikūni": "alāku", "qabal": "qablu", "maškir": "maškuru", "Dur-Ladini": "Dur-Ladini", "nuttammīši": "namāšu", "Bab-bitqi": "Bab-bitqi", "nētitīqi": "etēqu", "šummu": "šumma", "lētiqu": "etēqu", "lilqiu": "leqû", "Balassu": "Balassu", "Nadinu": "Nadinu", "maškirī": "maškuru", "šaknu": "šaknu", "lunammišu": "namāšu", "urkiūte": "arkû", "Dur-Balihaya": "Dur-Balihaya", "abbakkanni": "abāku", "egerāte": "egertu", "rāqu": "rīqu", "tahūme": "tahūmu", "adaggal": "dagālu", "kilallē": "kilallān", "iddūku": "dâku", "ussalbi": "lawû", "immerēya": "immeru", "ihbutūni": "habātu", "Arzaya": "Arzaya", "ihtabatūšunu": "habātu", "ēṣadī": "ēṣidu", "aqrûni": "qerû", "Amurru-šumu-iškun": "Amurru-šumu-iškun", "qibīma": "qabû", "šarrumma": "šarru", "Kihudaksi": "Kihudaksi", "maṣṣartaki": "maṣṣartu", "Mišarru-naṣir": "Mišaru-naṣir", "tādurma": "adāru", "upallahma": "palāhu", "tapallahma": "palāhu", "nakutti": "naquttu", "taraššu": "rašû", "mātimma": "mātu", "pūtūma": "pūtu", "našāt": "našû", "gudūdānu": "gudūdu", "Aššur-eṭir": "Aššur-eṭir", "šitta": "šina", "narkabāti": "narkabtu", "iltapru": "šapāru", "pānīki": "pānu", "ušuzzu": "ušuzzāyu", "iṣṣidi": "eṣēdu", "ebūru": "ebūru", "šiprānūwa": "šipru", "Dummal": "Tummal", "illûni": "elû", "paqdūnikku": "paqdu", "uṣurma": "naṣāru", "qīpu": "qīpu", "iṣabbatūšunūtu": "ṣabātu", "šalimdi": "šalmu", "šēpēšunu": "šēpu", "šukunma": "šakānu", "šulummêšunu": "šulummû", "šupraššunūtu": "šapāru", "kurību": "kurību", "tādur": "adāru", "kurru": "kurru", "šamaššammē": "šamaššammū", "Šamaš-ereš": "Šamaš-ereš", "ultēbilakku": "wabālu", "Ah-aba": "Ah-abi", "Karlaya": "Karallaya", "Kalzi": "Kilizi", "erraba": "erēbu", "maddattušu": "maddattu", "qātīšu": "qātu", "ša-qurbūte": "ša-qurbūti", "ihirūpu": "harāpu", "ētiqa": "etēqu", "nāru": "nāru", "ušebbāra": "ebēru", "etteqa": "etēqu", "Asdudaya": "Asdudaya", "muhhīya": "muhhu", "issapar": "šapāru", "Qadarua": "Qadarua", "Lidu": "Lidu", "Hadidu": "Hadidu", "adê": "adû", "attahāra": "mahāru", "mētu": "mītu", "Nabu-eṭiranni": "Nabu-eṭiranni", "iškunannīni": "šakānu", "šuh": "šuh", "Ullubaya": "Ullubaya", "assaʾal": "šâlu", "šaṣbutu": "šaṣbutu", "karim": "karmu", "muṭêšu": "muṭû", "unammaš": "namāšu", "uttammīši": "namāšu", "emūqīya": "emūqu", "liqbâššunu": "qabû", "mardiāti": "mardītu", "illak": "alāku", "mušēṣiu": "mušēṣû", "mīlu": "mīlu", "ētetiq": "etēqu", "adrāʾi": "durāʾu", "hūṭa": "haṭāṭu", "pitte": "pitti", "nārī": "nāru", "kaqquru": "qaqqaru", "matih": "mathu", "haṭāṭi": "haṭāṭu", "ṭēmi": "ṭēmu", "šar": "šarru", "Elamti": "Elamtu", "ētibir": "ebēru", "gišri": "gišru", "isseme": "šemû", "Deri": "Deru", "Zineni": "Zineni", "ussahhira": "sahāru", "emūqēšu": "emūqu", "ugdatammeru": "gamāru", "dātuššu": "dāt", "Adad-kaʾʾin-aplu": "Adad-kaʾʾin-aplu", "Arime": "Arumu", "urtakkis": "rakāsu", "ušēli": "elû", "pānātukka": "pānātu", "bīrtu": "birtu", "ugammar": "gamāru", "šukkalli": "šukkallu", "egirāti": "egertu", "ušēbilanni": "wabālu", "Amel-Illil": "Amel-Illil", "ittūbil": "wabālu", "ṭēmunni": "ṭēmu", "ašappāra": "šapāru", "rēhtu": "rēhtu", "sūti": "sūtu", "iqṭibûni": "qabû", "nušākal": "akālu", "šatti": "šattu", "ilku": "ilku", "laddin": "tadānu", "karāni": "karānu", "akannīma": "akanni", "lušālikšunu": "alāku", "lizbilu": "zabālu", "bēlīšu": "bēlu", "niqî": "nīqu", "išpura": "šapāru", "iltēn": "ištēn", "yābilu": "yābilu", "Zarpanitu": "Zarpanitu", "attadin": "nadānu", "Mar-biti": "Mar-biti", "ittašiz": "izuzzu", "libbī": "libbu", "ibtalṭa": "balāṭu", "aktarab": "karābu", "attūridi": "arādu", "untaggir": "mugguru", "assarap": "šarāpu", "attatāha": "matāhu", "aktarāra": "karāru", "ša-bēt-kūdin": "ša-bēt-kūdini", "šallūtu": "šallatu", "Mazamua": "Mazamua", "lūparriša": "parāsu", "Kanunaya": "Kanunayu", "urradūni": "arādu", "lūnammēši": "namāšu", "Nabu-belu-kaʾʾin": "Nabu-belu-kaʾʾin", "Manni-laddinni": "Mannu-laddin", "lukīnūni": "kânu", "pāni": "pānu", "dūru": "dūru", "gammur": "gammuru", "nāṭu": "nāṭu", "abi": "abu", "ētapšu": "epēšu", "šibirni": "šebru", "qīru": "qīru", "paššu": "paššu", "māhirī": "māhiru", "abulli": "abullu", "šaknat": "šaknu", "uppu": "uppu", "sikkūru": "sikkūru", "epšu": "epšu", "bībī": "bīʾu", "kisallu": "kisallu", "kupru": "kupru", "kapru": "kapru", "darīki": "darīku", "napṭarte": "napṭartu", "raṣip": "raṣpu", "ṣallulu": "ṣullulu", "qātī": "qātu", "araṣṣip": "raṣāpu", "ebirtu": "epertu", "akappar": "kapāru", "ša-bīrte": "ša-bīrāti", "raṣpa": "raṣpu", "gammura": "gamru", "ūrāte": "ūru", "isirru": "sêru", "bisannāte": "pišannu", "išakkunu": "šakānu", "tarbāṣāte": "tarbaṣu", "ikassiru": "kasāru", "yarhu": "yarhu", "gīdāni": "kīdānu", "damqu": "damqu", "addanniš": "adanniš", "appār": "appāru", "emmar": "amāru", "bābu": "bābu", "taqmi": "qamû", "harbī": "harbu", "šugurrī": "šugurru", "hamartu": "hamartu", "būlu": "būlu", "maṣṣarti": "maṣṣartu", "ušerrab": "erēbu", "ašakkan": "šakānu", "lillikūnu": "alāku", "lērubu": "erēbu", "imattāha": "matāhu", "ētamar": "amāru", "Raṣappi": "Raṣappa", "Arzuhinu": "Arzuhina", "šaknūti": "šaknu", "ṣābānišunu": "ṣābu", "rēṣūtīya": "rēṣu", "ušallak": "alāku", "alqi": "leqû", "manû": "manû", "ṭātu": "ṭātu", "tallakki": "tallakku", "kurrayâ": "kurru", "tallik": "alāku", "hūli": "hūlu", "šūnu": "šunu", "kallu": "kalû", "kurraya": "kurru", "immarrakku": "namarkû", "ipallāha": "palāhu", "padānī": "padānu", "laṣbassu": "ṣabātu", "Sin-ašared": "Sin-ašared", "Mar-Zeri": "Mar-Zeri", "pēthallu": "pēthallu", "māhiṣānīšu": "māhiṣu", "šapte": "šaptu", "batte": "battu", "ammete": "ammiu", "kammusu": "kamsu", "anīnu": "anīnu", "karānu": "karānu", "issaknūšu": "šakānu", "siliēte": "silītu", "pānātūwa": "pānātu", "ušaṣbit": "ṣabātu", "eleppātēya": "eleppu", "attūṣi": "aṣû", "ēnī": "īnu", "ittūṣûni": "aṣû", "assapraššunu": "šapāru", "Larakaya": "Larakaya", "ittannūni": "tadānu", "ušēṣûni": "aṣû", "ussanetteqūšu": "etēqu", "urkītišunu": "warkītu", "addagal": "dagālu", "iddanūni": "tadānu", "ṭēnšanūni": "ṭēmu", "aqabbi": "qabû", "Addari": "Addaru", "ittibi": "tebû", "Nabu-naṣir": "Nabu-naṣir", "ṭēmūni": "ṭēmu", "Nisanni": "Nisannu", "Sin-ahhe-eriba": "Sin-ahhe-eriba", "ēkurrāte": "ēkurru", "bīrāt": "birtu", "radāpi": "radāpu", "ṣarpumma": "ṣarpu", "kili": "kalû", "mugirrī": "mugerru", "Marad": "Marad", "uttammiš": "namāšu", "Parak-Mari": "Parak-Mari", "Nippuraya": "Nippuraya", "ātašar": "ašāru", "ubbal": "wabālu", "apaqqid": "paqādu", "Dalta": "Dalta", "uṣṣā": "aṣû", "errab": "erēbu", "assēme": "šemû", "rēhte": "rēhtu", "maddatte": "maddattu", "upahhar": "pahāru", "bilassu": "biltu", "iddana": "tadānu", "Mataya": "Madaya", "paṭṭuru": "puṭṭuru", "attaṣa": "našû", "Zakrutu": "Zakrutu", "iqṭibiu": "qabû", "niddan": "tadānu", "rabiūti": "rabiu", "lišpur": "šapāru", "Kuluman": "Kuluman", "Elamtu": "Elamtu", "dalhu": "dalhu", "kettu": "kittu", "issaprūni": "šapāru", "kitrī": "kitru", "Ellipi": "Ellipi", "ētabku": "abāku", "ētarab": "erēbu", "illuku": "alāku", "dāmu": "dāmu", "nirtiṣīpi": "raṣāpu", "lallik": "alāku", "iktalaššu": "kalû", "lišʾullu": "šâlu", "ketti": "kittu", "pilkušu": "pilku", "unaʾʾada": "nâdu", "ilu": "ilu", "pilku": "pilku", "emid": "emdu", "epšeti": "epištu", "annīti": "annû", "mala": "mala", "Nergal-eṭir": "Nergal-eṭir", "Hunanu": "Hunanu", "iddubūbu": "dabābu", "ibaššûnu": "bašû", "Kar-Šarrukin": "Kar-Šarrukin", "idabbubu": "dabābu", "ūmu": "ūmu", "ettēqe": "etēqu", "ṣāssu": "ṣāltu", "hinsāte": "himsātu", "iggarraninni": "gerû", "ša-rēšāni": "ša-rēši", "eppušūni": "epēšu", "Kulnia": "Kullania", "Dur-Bel-ilaʾi": "Dur-Bel-ilaʾi", "iqribūninni": "qerēbu", "māte": "mātu", "urradūninni": "arādu", "imuttu": "mâtu", "Mušallim-Marduk": "Mušallim-Marduk", "nišēšu": "nišu", "ettiq": "etēqu", "uššab": "ašābu", "ašapparūni": "šapāru", "ušabâdaššunni": "biātu", "itabbiu": "tebû", "Qarnina": "Qarnina", "Harammu": "Harammu", "līmi": "līm", "assapāraššu": "šapāru", "muk": "muk", "Quwe": "Quwe", "sūsānī": "šušānu", "qātēšunu": "qātu", "pîšu": "pû", "iṣṣabtu": "ṣabātu", "nagiu": "nagû", "liṣṣur": "naṣāru", "ussēšibšunu": "ašābu", "bētātišunu": "bītu", "idaggulu": "dagālu", "idaggalūni": "dagālu", "lidgulu": "dagālu", "lišme": "šemû", "bābāni": "bābu", "lupatte": "petû", "innamerāni": "amāru", "gabbīšu": "gabbu", "mūšu": "mūšu", "zunnī": "zunnu", "izzunūnu": "zanānu", "zīnu": "zinnu", "iktarāra": "karāru", "nību": "nību", "šammī": "šammu", "issiqi": "leqû", "Arbail": "Arbail", "anākūni": "anāku", "ussanniʾa": "šanû", "šanuttēšu": "šanûtī-", "Aššur-naṣir": "Aššur-naṣir", "Am-hati": "Ammi-hati", "Bel-apkal-ilani": "Bel-apkal-ilani", "mušarkisāni": "mušarkisu", "Bel-aplu-iddina": "Bel-aplu-iddina", "ētarbu": "erēbu", "turtāni": "tartānu", "bīrātīya": "birtu", "sissêya": "sisû", "ūmātīya": "ūmu", "rabîya": "rabiu", "šanîya": "šanû", "atta": "atta", "kūmūwa": "kūm", "maṣṣartāka": "maṣṣartu", "tašīaṭ": "šâṭu", "uṣur": "naṣāru", "egertu": "egertu", "annītu": "annû", "tammarūni": "amāru", "idūkanni": "dâku", "Aššur-ilaʾi": "Aššur-ilaʾi", "tēlit": "tēlītu", "adrišunu": "adru", "memmēnīma": "memēni", "ardēka": "ardu", "Nabu-nammir": "Nabu-nammir", "bēlīni": "bēlu", "nillik": "alāku", "bēlīnīma": "bēlu", "išpurannāši": "šapāru", "dullumma": "dullu", "epšā": "epēšu", "ahāmeš": "ahāmiš", "līpušāma": "epēšu", "mamma": "mamman", "ušanhassu": "mahāṣu", "muhhīšu": "muhhu", "ṣābu": "ṣābu", "tamirti": "tawwertu", "anaddû": "nadû", "issihu": "sehû", "Kaldu": "Kaldu", "āpiu": "ēpû", "šakinte": "šakintu", "haṭṭu": "haṭṭu", "tupninnu": "tupninnu", "kanūnu": "kinūnu", "parzilli": "parzillu", "asallu": "asallu", "siparru": "siparru", "šarqu": "šarqu", "kaspi": "kaspu", "tadānu": "tadānu", "tadinūnu": "tadnu", "bātequ": "bātiqu", "ašpuranni": "šapāru", "lammarku": "namarkû", "lupahhira": "pahāru", "nasīkāti": "nasīku", "ašsaʾal": "šâlu", "rēhe": "rēhu", "annūtimma": "annû", "lišʾalšunu": "šâlu", "Remanni-Issar": "Remanni-Issar", "mardēti": "mardītu", "irtīni": "irtu", "ēteliʾa": "elû", "šākil": "akālu", "mati": "mati", "abattaq": "batāqu", "šarrê": "šarru", "šaddaqdiš": "šaddaqda", "ašpurru": "šapāru", "iqṭibiʾa": "qabû", "tahhuranni": "mahāru", "addinakka": "tadānu", "ūdâ": "wadû", "kurummitī": "kurummatu", "laššūni": "laššu", "liddinūni": "tadānu", "liddinu": "tadānu", "urkīʾu": "arkû", "addanaššunu": "tadānu", "išsēya": "išti", "lušanšilu": "mašālu", "lušanšil": "mašālu", "akê": "kē", "karmu": "karmu", "dūrāni": "dūru", "ussarīqu": "riāqu", "lurammî": "ramû", "nikallašunu": "kalû", "attalka": "alāku", "libīt": "liwītu", "ili": "ilu", "ša-pēthalli": "ša-pēthalli", "dāte": "dāt", "Sarun": "Sarun", "aqṭirib": "qerēbu", "akarrāra": "karāru", "allak": "alāku", "Birdunu": "Birdunu", "Urarṭi": "Urarṭu", "Etiniaya": "Etiniaya", "izzuqūpu": "zaqāpu", "dēktušu": "dīktu", "iddūak": "dâku", "hubtušu": "hubtu", "ihtabat": "habātu", "šalšūtīšu": "šalšūtī-", "Ṭurušpa": "Ṭurušpa", "ētašira": "ešēru", "ishur": "sahāru", "Suruduriani": "Sarduriani", "Zaba": "Zaba", "azqupūni": "zaqāpu", "ša-killi": "ša-kallî", "šalāšīšu": "šalāšī-", "mītīya": "mītu", "ṭēmā": "ṭēmu", "la-pān": "lapān", "iptesnu": "pesēnu", "agannîmma": "agannû", "lihsus": "hasāsu", "marṣāku": "marṣu", "madāktu": "madaktu", "šakan": "šaknu", "amūt": "mâtu", "ukkušu": "kâšu", "aklū": "akalu", "alhim": "lehēmu", "bēlā": "bēlu", "minû": "mīnu", "tašpura": "šapāru", "altapar": "šapāru", "šēpēšu": "šēpu", "ṭēmumma": "ṭēmu", "babbanû": "babbanû", "iqīpuʾinni": "qiāpu", "uhtammû": "hamû", "ša-qurrubūti": "ša-qurbūti", "qulālī": "qulālu", "ubbalu": "wabālu", "liqbīma": "qabû", "ipaqqidanni": "paqādu", "Larak": "Larak", "ūṣâʾ": "aṣû", "īdī": "wadû", "ahhēya": "ahu", "nišēya": "nišu", "anašši": "našû", "addan": "tadānu", "akannî": "akanni", "assabar": "šapāru", "marīṣi": "marṣu", "ahūšu": "ahu", "šarrēšu": "šarru", "izzaz": "izuzzu", "niptuhur": "pahāru", "nittetēzi": "izuzzu", "ahāʾiš": "ahāmiš", "abullāti": "abullu", "niqṭirib": "qerēbu", "dēktu": "dīktu", "niddūak": "dâku", "dēke": "dīku", "Šumu-ukin": "Šumu-ukin", "māršu": "māru", "kašdu": "kašdu", "hadi": "hadû", "šiprīni": "šipru", "lidgul": "dagālu", "ilāni": "ilu", "ammutu": "ammatu", "rūṭu": "rūṭu", "errabūni": "erēbu", "muhhu": "muhhu", "Marduk-apla-iddina": "Marduk-apla-iddina", "ēmurūni": "amāru", "ubbalūni": "wabālu", "iqbīma": "qabû", "šiprīka": "šipru", "ṭēnga": "ṭēmu", "pesnu": "pesnu", "šipirti": "šipirtu", "ašapparakkamma": "šapāru", "gabri": "gabarû", "tušebbila": "wabālu", "šipirtā": "šipirtu", "šarrāni": "šarru", "šiprānīya": "šipru", "ušettiq": "etēqu", "ušēṣašu": "aṣû", "bīt": "bītu", "tallika": "alāku", "gabrâšu": "gabarû", "aṣ̌ṭur": "šaṭāru", "ultēbil": "wabālu", "ušettiqšūma": "etēqu", "hīṭu": "hīṭu", "ardīšu": "ardu", "Habban": "Bit-Hamban", "iqṭarba": "qerēbu", "ētabra": "ebēru", "ugdadammer": "gamāru", "numammāša": "namāšu", "nillak": "alāku", "lēʾāni": "lēʾu", "nībāni": "nību", "iṣṣabatma": "ṣabātu", "šiprīšu": "šipru", "nībuk": "abāku", "Ištar": "Ištar", "Hasuatti": "Hasuatti", "pāniūti": "pānû", "urkiūti": "arkû", "sartenni": "sartennu", "kunukku": "kunukku", "battabatti": "battubattu", "Qurdi-Aššur": "Qurdi-Aššur", "Aya-nuri": "Aya-nuri", "Dabinaya": "Dabinaya", "Ezazu": "Ezazu", "šumšu": "šumu", "ubbala": "wabālu", "kanīkišu": "kanīku", "Maʾabaya": "Maʾabaya", "Gidiraya": "Qidiraya", "Maʾaba": "Maʾab", "ētiqūni": "etēqu", "idūkūni": "dâku", "aptiqissu": "paqādu", "ubbalaššu": "wabālu", "Šabaṭi": "Šabaṭu", "uṣṣūni": "aṣû", "emūqāni": "emūqu", "emūqāka": "emūqu", "Dur-Tinuta": "Dur-Tinuta", "udīna": "udīni", "aqarrībi": "qerēbu", "Barsibitu": "Barsipitu", "qēpi": "qīpu", "tassapāra": "šapāru", "tussēbila": "wabālu", "tadūku": "dâku", "gabrû": "gabarû", "kanīki": "kanīku", "assaṭar": "šaṭāru", "šakinūni": "šaknu", "emmuru": "amāru", "dullī": "dullu", "ugdammir": "gamāru", "ūdāma": "wadû", "šāša": "šâša", "amahharšīni": "mahāru", "tušēbilanni": "wabālu", "ṣīri": "ṣīru", "maṣṣartušu": "maṣṣartu", "uddaʾʾin": "danānu", "ittuqut": "maqātu", "iṣṣabtuniššu": "ṣabātu", "ušēbilaššu": "wabālu", "Yadiʾ-ilu": "Yadiʾ-il", "ihtiliq": "halāqu", "bēssu": "bītu", "Hindana": "Hindanu", "Adad-aplu-iddina": "Adad-aplu-iddina", "uṣabbūtu": "ṣabātu", "ušebbalūni": "wabālu", "parakku": "parakku", "liqiba": "qabû", "qablēka": "qablu", "rukus": "rakāsu", "itizi": "izuzzu", "bīli": "wabālu", "ittībūlu": "wabālu", "darâ": "darrû", "immeru": "immeru", "kaqqidi": "qaqqadu", "ittikis": "nakāsu", "Nabu-šumu-iškun": "Nabu-šumu-iškun", "šanīš": "šanîš", "qīti": "qītu", "itūru": "târu", "libbīšu": "libbu", "kallê": "kallû", "ultaṣbat": "ṣabātu", "īdû": "wadû", "abīya": "abu", "ardānu": "ardu", "qablēnu": "qablu", "raksa": "raksu", "liṣrim": "ṣarāmu", "luddin": "nadānu", "lušmēma": "šemû", "luhma": "hamû", "kīnu": "kīnu", "mātu": "mātu", "uṭṭatīya": "uṭṭatu", "mahru": "mahru", "suhhiramma": "sahāru", "lūbuk": "abāku", "šulum": "šulmu", "lušmi": "šemû", "Ilu-mušezib": "Ilu-mušezib", "Bel-emuranni": "Bel-emuranni", "Hatarikka": "Hatarikka", "ussēšibšu": "ašābu", "Kubaba-ereš": "Kubaba-ereš", "kalzīšu": "kalzu", "kalzi": "kalzu", "ussahliqu": "halāqu", "lišʾulu": "šâlu", "amēlu": "awīlu", "lusahhirūni": "sahāru", "mūtānu": "mūtānu", "annākāni": "annaka", "Ilu-biʾdi": "Ilu-biʾdi", "kiṣir": "kiṣru", "qātēya": "qātu", "sissû": "sisû", "iddūka": "dâku", "ussalimme": "šalāmu", "addanakka": "tadānu", "issušu": "sinništu", "hurdu": "hurdu", "marʾu": "māru", "qallu": "qallu", "tātahaz": "ahāzu", "nuhatimmī": "nuhatimmu", "iddūla": "dâlu", "Tuqunu": "Tuqunu", "Kimumaya": "Kimumaya", "lišʾāla": "šâlu", "šūtūni": "šūtu", "Nabu-šezib": "Nabu-šezib", "ṭupšarru": "ṭupšarru", "Aššur-ereš": "Aššur-ereš", "lušēbilšu": "wabālu", "Šamaš-ilaʾi": "Šamaš-ilaʾi", "mātīka": "mātu", "Aššur": "Aššur", "Šamaš": "Šamaš", "iškunnannīni": "šakānu", "luṣabbitu": "ṣabātu", "bīlāni": "wabālu", "ettīqi": "etēqu", "arad": "ardu", "aššassu": "aššatu", "Bel-iddina": "Bel-iddina", "Lu-gamil": "Lu-gamil", "Bel-hutu": "Bel-hutu", "aššat": "aššatu", "Marduk-šallimanni": "Marduk-šallimanni", "Yansiatu": "Yansiatu", "amtu": "amtu", "Pî-itarru": "Pî-itarru", "Dur-ša-Balihaya": "Dur-Balihaya", "Hamapi": "Hamapi", "qīpi": "qīpu", "Bit-Imbiya": "Bit-Imbiya", "ašbu": "ašbu", "madākti": "madaktu", "arkīšu": "arki", "altapraššu": "šapāru", "dīkatšunu": "dīktu", "iddūk": "dâku", "qātēka": "qātu", "umallû": "malû", "Šapia": "Sapia", "taptaṭaršu": "paṭāru", "šāšūma": "šâšu", "manni": "mannu", "amatka": "awātu", "ittiqû": "etēqu", "adêka": "adû", "ušannû": "šanû", "immanni": "manû", "Šulmu-beli": "Šulmu-beli", "Urarṭaya": "Urarṭaya", "naṣāni": "našû", "libbimmâ": "libbu", "nubbalšunu": "wabālu", "pēthalli": "pēthallu", "akṣurūni": "kaṣāru", "iškār": "iškāru", "annīte": "annû", "tankarāni": "tamkāru", "ēmedūni": "emēdu", "tassalap": "šalāpu", "hannî": "annû", "libbīka": "libbu", "tadbub": "dabābu", "iškāru": "iškāru", "ihalliqu": "halāqu", "šiprānīšu": "šipru", "Zakir": "Zakiru", "ma": "mannu", "attâ": "atta", "reʾsāni": "raʾsu", "Kaldi": "Kaldu", "rēhākāni": "rēhu", "qālāka": "qālu", "isammu": "samû", "mahēre": "mahru", "hapê": "hepû", "naṣūninni": "našû", "ittablūni": "tabālu", "issisiu": "šasû", "iptalah": "palāhu", "tallaka": "alāku", "šagalanni": "galû", "ahātīya": "ahātu", "anakkir": "nakāru", "išaddāda": "šadādu", "ihappi": "hepû", "unnāka": "annaka", "Malilataya": "Malilataya", "aharrīdi": "harādu", "ebrāni": "ebēru", "kulda": "kašādu", "tibbira": "ebēru", "ṭābūti": "ṭābu", "niddubub": "dabābu", "ayālê": "ayyalu", "ayālīka": "ayyalu", "ikkê": "kē", "nillaka": "alāku", "lušarhiṣūšu": "rahāṣu", "igalliu": "galû", "Attua": "Attua", "aqabûni": "qabû", "ittūṣia": "aṣû", "issuhur": "sahāru", "abūšu": "abu", "Gurraya": "Gurraya", "ilsumūni": "lasāmu", "Hardi": "Hardu", "adakāni": "adakanni", "ūṣīu": "aṣû", "mehrīšunu": "mehru", "illiku": "alāku", "urdānīya": "ardu", "Naba": "Naba", "išpurūni": "šapāru", "ussahhir": "sahāru", "iddin": "tadānu", "Manisaya": "Manisaya", "ramanīšunu": "ramānu", "Wayaniara": "Wayaniara", "lahhī": "lahhu", "ihhurūni": "mahāru", "allakāni": "alāku", "aqṭibāšu": "qabû", "alka": "alāku", "iddanakkanni": "tadānu", "ashurāni": "sahāru", "ipqidūni": "paqādu", "māssu": "mātu", "ēmur": "amāru", "dīnšūni": "dīnu", "aqṭibaššu": "qabû", "alê": "ali", "pānēkāni": "pānu", "išmûni": "šemû", "kilallīšunu": "kilallān", "šulme": "šulmu", "dātūwa": "dāt", "ukâllûni": "kullu", "ahīšunu": "ahu", "nagê": "nagû", "ittābalu": "wabālu", "iraʾʾûni": "reʾû", "kūmi": "kūm", "sarte": "sartu", "ihtabtu": "habātu", "ukâllu": "kullu", "liškunanni": "šakānu", "Kurbail": "Kurbail", "nasīkāni": "nasīku", "akabbusūni": "kabāsu", "assapāra": "šapāru", "ihtiṭiu": "haṭû", "tattanaqqi": "naqû", "lēpūšu": "epēšu", "Muqallil-kabti": "Muqallil-kabti", "Našmedi": "Našmedi", "Adad-killanni": "Adad-killanni", "sangî": "šangû", "Dur-Illil": "Dur-Illil", "Tatu": "Tatu", "Kapar-Ilu-bani": "Kapar-Ilu-bani", "mušarkis": "mušarkisu", "Ahu-iddina": "Ahu-iddina", "Singar": "Singara", "parriṣūti": "parriṣu", "Ša-Nashur-Bel": "Ša-Nashur-Bel", "igdaldu": "galātu", "Hu-Teššub": "Hu-Teššub", "Mušeṣi": "Mušeṣi", "ahūwa": "ahu", "islimūni": "salāmu", "ūdāšu": "wadû", "iškāršu": "iškāru", "libbīya": "libbu", "pāhatūtēya": "pīhātūtu", "tūra": "tūra", "ihabbura": "habāru", "allāka": "alāku", "uramma": "ramû", "Argue": "Argue", "Kinnili": "Kinnili", "Šarru-emuranni": "Šarru-emuranni", "Isana": "Isana", "nusāhī": "nusāhu", "šaššūme": "šalšūmi", "Barruqu": "Barruqu", "ninassahūni": "nasāhu", "qēpāni": "qīpu", "uktaššīdi": "kašādu", "ša-qurbūtu": "ša-qurbūti", "zakû": "zakû", "eqlu": "eqlu", "lukīn": "kânu", "ilqûni": "leqû", "nusāhīni": "nusāhu", "tadāni": "tadānu", "balṭu": "balṭu", "nuhatimmi": "nuhatimmu", "uktaššidu": "kašādu", "ṣabitūni": "ṣabtu", "ittashu": "nasāhu", "uktaššid": "kašādu", "masennu": "mašennu", "iptuāga": "puāgu", "zarʾīni": "zēru", "ekkal": "akālu", "laddīni": "tadānu", "nusāhīnīni": "nusāhu", "liššiʾa": "našû", "Baqarma": "Baqar", "izakkar": "zakāru", "zakûka": "zakû", "ussērībi": "erēbu", "Šep-Aššur": "Šep-Aššur", "Etuʾu": "Ituʾaya", "gimrumma": "gimru", "adêšunu": "adû", "Dimašqi": "Dimašqa", "uṣṣabbitu": "ṣabātu", "ussēbilaššunu": "wabālu", "māhiṣāni": "māhiṣu", "danqūti": "damqu", "šandabakku": "šandabakku", "Enlil": "Enlil", "Ninurta": "Ninurta", "Nusku": "Nusku", "Bit-Aššur": "Bit-Aššur", "rēhēt": "rēhtu", "balāṭi": "balāṭu", "napšāti": "napištu", "kalla": "kallû", "ušēbila": "wabālu", "kitti": "kittu", "ardēya": "ardu", "danān": "danānu", "annîmma": "annû", "adī": "adi", "iṣi": "iṣu", "nagû": "nagû", "iṣī": "iṣu", "našû": "našû", "anaṣṣar": "naṣāru", "māhiṣīšu": "māhiṣu", "lizqup": "zaqāpu", "Mušallim-Aššur": "Mušallim-Aššur", "Ṣimerra": "Ṣimirra", "ittūra": "târu", "mētūti": "mītu", "dullašunu": "dullu", "ṣabat": "ṣabātu", "gamir": "gamru", "issēt": "ištēn", "eleppu": "eleppu", "iṣî": "iṣu", "ātašaršunu": "ašāru", "ūtassik": "esēhu", "ussēṣiaššunu": "aṣû", "ittatakkūni": "alāku", "gammalu": "gammalu", "Lidiaya": "Lidiaya", "Utuʾaye": "Ituʾaya", "Hamaraye": "Hamaraya", "Šamaš-naṣir": "Šamaš-naṣir", "Aššur-remanni": "Aššur-remanni", "Taku": "Taku", "Lulubani": "Lulubani", "Mila": "Mila", "nišēka": "nišu", "šēṣiʾa": "aṣû", "lušērībi": "erēbu", "ammaggur": "magāru", "ammarūni": "amāru", "urraš": "erēšu", "Pirriya": "Pirriya", "harbi": "harbu", "rēʾî": "rēʾû", "šahû": "šahû", "ayalī": "ayyalu", "arāši": "erēšu", "Hattimma": "Hatti", "ekkulu": "akālu", "kurummutu": "kurummatu", "attanarraš": "erēšu", "ālānīšu": "ālu", "Hašdat": "Hašdat", "Arpadda": "Arpadda", "birituššunu": "birti", "parku": "parku", "ittiši": "našû", "ātaraš": "erēšu", "lēṣīdi": "eṣēdu", "nīri": "nīru", "lēkulu": "akālu", "sissî": "sisû", "ayēša": "ayyiša", "lūbil": "wabālu", "ussanniqūni": "sanāqu", "upahhuru": "pahāru", "errišâ": "erēšu", "pānīyāni": "pānu", "akalla": "kalû", "ussēṣa": "aṣû", "uttarāte": "attartu", "kūdinī": "kūdanu", "urāte": "urû", "mukīl": "mukillu", "appāti": "appatu", "tašlīšāni": "tašlīšu", "damqi": "damqu", "ša-pēthallāte": "ša-pēthalli", "zunzurahhī": "zunzurahhu", "ša-bēti-šanie": "ša-bēti-šanie", "kāṣirī": "kāṣiru", "karkadinnī": "kakardinnu", "āpiāni": "ēpû", "nuhatimmu": "nuhatimmu", "ummânī": "ummiānu", "mutīr": "muterru", "kalbāte": "kallāpu", "Gurru": "Gurraya", "Itu": "Ituʾaya", "bētīya": "bītu", "namarku": "namarkû", "Masʾaya": "Masʾaya", "iškunanni": "šakānu", "Nashir-Bel": "Nashir-Bel", "nussatammeh": "samāhu", "pūtuššu": "pūtu", "nēpuš": "epēšu", "hannākamma": "annaka", "ṣīlti": "ṣāltu", "annākamma": "annaka", "ēṣūtēma": "īṣu", "sartinni": "sartennu", "šiprātēya": "šipru", "ašappar": "šapāru", "eqlāti": "eqlu", "inaššûninni": "našû", "issāti": "sinništu", "lušāhizušunu": "ahāzu", "ātamar": "amāru", "abbēšina": "abu", "immagguru": "magāru", "iddunūšina": "tadānu", "kaspu": "kaspu", "iddanūnāšīni": "tadānu", "liddinūniššunu": "tadānu", "lēhuzu": "ahāzu", "Ubru-Libbali": "Ubru-Libbali", "inbu": "inbu", "Kiṣirte": "Kiṣirtu", "talaqqi": "leqû", "Aššur-mušallim": "Aššur-mušallim", "Nergal-mušallim": "Nergal-mušallim", "ahhē": "ahu", "alaqqi": "leqû", "šāqû": "šāqû", "dāti": "dāt", "lēʾi": "lēʾu", "šaṭrat": "šaṭru", "kaqqadāte": "qaqqadu", "kētu": "kittu", "šīte": "šīti", "iqanâni": "qanû", "kalbu": "kalbu", "kette": "kittu", "ētapšanni": "epēšu", "kēte": "kittu", "Bel-ahu-uṣur": "Bel-ahu-uṣur", "Ubru-ahhe": "Ubru-ahhe", "kiriu": "kirû", "ayu": "ayyu", "ṣehri": "ṣehru", "hūlāni": "hūlu", "ebbir": "ebēru", "irti": "irtu", "lurammešunû": "ramû", "lēbirnê": "ebēru", "laklašunu": "kalû", "maṣṣartaka": "maṣṣartu", "uttīru": "târu", "Bur-il": "Bur-il", "ittuqta": "maqātu", "Bar-Uri": "Bar-Uri", "ūmāya": "ūmāya", "mâri": "mâru", "pursītu": "pursītu", "šamnī": "šamnu", "tadin": "tadnu", "purṭīe": "purdû", "epinnāti": "epinnu", "patakkāti": "padakku", "urīṣāni": "urīṣu", "Arahsamni": "Arahsamnu", "ša-šīmī": "ša-šīmi", "išammu": "šâmu", "limūtu": "mâtu", "tabku": "tabku", "zakkê": "zakkû", "išû": "išû", "tuṣṣā": "aṣû", "šaniūti": "šanû", "qarbatu": "qerbetu", "rabiu": "rabû", "uppuqu": "uppuqu", "būrtu": "būrtu", "uptaṭṭir": "paṭāru", "iraṣṣip": "raṣāpu", "qarbiti": "qerbetu", "rabie": "rabû", "Dahini": "Dahinu", "nērubu": "nērebu", "hirīṣu": "harīṣu", "ihruṣa": "harāṣu", "rapšu": "rapšu", "rūqu": "rūqu", "sūsānu": "šušānu", "assabaršu": "šapāru", "Kalha": "Kalhu", "erba": "erēbu", "nipatti": "petû", "kupû": "kuppû", "umalla": "malû", "iddiʾin": "danānu", "šaluššēni": "šaluššani", "annimma": "annû", "idanna": "danānu", "kupê": "kuppû", "issīka": "išti", "adakanni": "adakanni", "nilaqqi": "leqû", "nubbal": "wabālu", "kalliu": "kallû", "Aššur-daʾʾinanni": "Aššur-daʾʾinanni", "Arzuhinaya": "Arzuhinaya", "luttīki": "etāku", "Aššur-nirka-daʾʾin": "Aššur-nirka-daʾʾin", "tūda": "wadû", "qinnī": "qinnu", "tartāni": "tartānu", "Birti": "Birtu", "iqibaššūni": "qabû", "kēnu": "kīnu", "tēraššu": "târu", "Sahiru": "Sahiru", "iqibânni": "qabû", "šanūni": "šunu", "ṣēnī": "ṣēnu", "išâm": "šâmu", "ūdaššunu": "wadû", "ittarṣakka": "tarāṣu", "qibi": "qabû", "Tašriti": "Tašritu", "Ṭebeti": "Ṭebetu", "lūrida": "arādu", "itarraṣūni": "tarāṣu", "dubbu": "dabābu", "eppašūni": "epēšu", "edānu": "edānu", "bitti": "pitti", "urradāni": "arādu", "Aššur-šimanni": "Aššur-šimanni", "Remute": "Remutu", "Nabu-reši": "Nabu-reši", "Nabi-rumu": "Nabe-rumu", "Nabu-šarhi-ilani": "Nabu-šarhi-ilani", "maṣi": "maṣû", "zarʾēšunu": "zēru", "tahūmu": "tahūmu", "ekkāla": "akālu", "talmīd": "talmīdu", "ušēlûni": "elû", "Nergal-ibni": "Nergal-ibni", "issakanannāši": "šakānu", "bētkunu": "bītu", "Huzirna": "Huzirina", "ṣabata": "ṣabātu", "arteṣībi": "raṣāpu", "anīni": "anīnu", "iškunnāšīni": "šakānu", "Mubi": "Mubi", "bētka": "bītu", "immaggurru": "magāru", "ṣabāte": "ṣabātu", "abīšu": "abu", "libbīni": "libbu", "ṣabāti": "ṣabātu", "uraṣṣipūni": "raṣāpu", "ušerrabūšunu": "erēbu", "karṣīya": "karṣu", "uhtalliqu": "halāqu", "Mannu-ki-Aššur": "Mannu-ki-Aššur", "zēru": "zēru", "ulla": "elû", "ušuzzāka": "ušuzzāyu", "maṣṣartā": "maṣṣartu", "qa": "qû", "Inurta-šarru-uṣur": "Inurta-šarru-uṣur", "sūtu": "sūtu", "Nabu-bel-ahhešu": "Nabu-bel-ahhešu", "addinakkanni": "tadānu", "tušaṣbitūni": "ṣabātu", "pāhatka": "pīhātu", "alpānika": "alpu", "immerēka": "immeru", "šaṣbutāka": "šaṣbutu", "tattahar": "mahāru", "tēteriš": "erēšu", "ušebbalkanni": "wabālu", "šēbir": "ebēru", "tušaṣbassunu": "ṣabātu", "hubti": "hubtu", "taddan": "tadānu", "šaṣbuti": "ṣabātu", "tašīaṭa": "šâṭu", "tamūat": "mâtu", "marṣu": "marṣu", "ušebbalakkanni": "wabālu", "rēqi": "rīqu", "maṭie": "maṭû", "ikarrurūšu": "karāru", "balṭūni": "balṭu", "kuzippī": "kuzippu", "kuzippīšunu": "kuzippu", "rāʾî": "rēʾû", "imittāti": "imittu", "zakkû": "zukkû", "Suru": "Suru", "uqṭarriba": "qerēbu", "šakin": "šaknu", "mallāhi": "malāhu", "Barsipaya": "Barsipaya", "Balassi": "Balassu", "izzuqpu": "zaqāpu", "mahhuṣu": "mahṣu", "dēku": "dīku", "damqīya": "damqu", "issišunūma": "išti", "Šarru-duri": "Šarru-duri", "mārīya": "māru", "Nabu-nadin-ahhe": "Nabu-nadin-ahhe", "Quraya": "Gurraya", "lēpušu": "epēšu", "Ganbulaya": "Gambulaya", "attanhaṣ": "mahāṣu", "annurag": "annûri", "Ša-Turmiš": "Ša-Turmiš", "Zaban": "Zaba", "karrāku": "karru", "Šarru-iqbi": "Šarru-iqbi", "Ša-Turmišaya": "Ša-Turmišaya", "nāgirāti": "nāgiru", "našûni": "našû", "Marduk-emuranni": "Marduk-emuranni", "gamāru": "gamāru", "Bani-Ani": "Bani-Ani", "sēhāni": "sēhû", "Dur-Kurigalzi": "Dur-Kurigalzu", "karṣīšu": "karṣu", "hīṭumma": "hīṭu", "patiāka": "patiu", "tattalka": "alāku", "iddūkūka": "dâku", "abutūma": "awātu", "ašmûni": "šemû", "āmarūni": "amāru", "aqṭibi": "qabû", "Lahiri": "Lahiru", "lušēribka": "erēbu", "inaṣṣarūni": "naṣāru", "ussēṣiu": "aṣû", "marʾiti": "mārtu", "marʾutu": "mārtu", "deʾiqtu": "damqu", "paššūru": "paššuru", "ušaṣbatšūni": "ṣabātu", "atturda": "arādu", "zūkī": "zūku", "Amiri": "Amiri", "anāqāte": "anāqutu", "uzzatakki": "zakû", "hubte": "hubtu", "ušettaqūni": "etēqu", "amaqqut": "maqātu", "Bel-iqbi": "Bel-iqbi", "issāhîši": "issahîš", "nittalak": "alāku", "ētamarnāši": "amāru", "šubtu": "šubtu", "kutallīni": "kutallu", "ussēšib": "ašābu", "nittahāṣa": "mahāṣu", "Huzaza": "Huzaza", "nirtidīpi": "radāpu", "Illabani": "Illabani", "niqṭirībi": "qerēbu", "nikšudūšu": "kašādu", "ahīyāma": "ahu", "iltime": "šemû", "mimmû": "mimmû", "taltakna": "šakānu", "ittīka": "itti", "idbubu": "dabābu", "mussīma": "wussû", "iltapra": "šapāru", "Bab-Barsip": "Bab-Barsip", "ušellû": "elû", "uṣṣīma": "aṣû", "erēšu": "erēšu", "nirriš": "erēšu", "birīt": "birīt", "sullim": "salāmu", "rāšānu": "raʾsu", "nilliku": "alāku", "sīsênu": "sisû", "nulteṣâ": "aṣû", "Mar-Yakinu": "Mar-Yakin", "urriha": "arāhu", "Mar-Yakin": "Mar-Yakin", "inaššû": "našû", "gabrî": "gabarû", "Budana": "Budana", "pirṣāta": "pirṣatu", "iddabubma": "dabābu", "ašpuru": "šapāru", "ittadi": "nadû", "ēkallu": "ēkallu", "tuttīr": "târu", "amangur": "magāru", "šanītu": "šanû", "tuttirru": "târu", "ṭuppu": "ṭuppu", "tutirru": "târu", "ašapparamma": "šapāru", "līpuš": "epēšu", "Iddin-ahi": "Iddin-ahi", "nittitīzi": "izuzzu", "mar-Babili": "mar-Babili", "Zasinnu": "Zasinnu", "Kaldaya": "Kaldaya", "issēšu": "išti", "mar-Babilaya": "mar-Babili", "niqṭibi": "qabû", "muhhikunu": "muhhu", "issaprannāši": "šapāru", "pîkunu": "pû", "ladbub": "dabābu", "durāri": "andurāru", "kidinnūtkunu": "kidinnūtu", "laškun": "šakānu", "maʾdūti": "mādu", "uṣṣûni": "aṣû", "issīni": "išti", "issanapparūnāši": "šapāru", "niqṭibaššunu": "qabû", "abullu": "abullu", "pitia": "petû", "nērub": "erēbu", "kanāšunu": "kunāšunu", "nussēribkunu": "erēbu", "ipattiu": "petû", "iqippu": "qiāpu", "paqdunikkunu": "paqdu", "Kar-Nergalma": "Kar-Nergal", "nishur": "sahāru", "nidabbub": "dabābu", "ṭēnšanūnu": "ṭēmu", "paṣiu": "peṣû", "nišappāra": "šapāru", "Litamaya": "Litamaya", "issaprūnāši": "šapāru", "ašarēdūtēni": "ašarēdu", "nubbalaššunu": "wabālu", "šūtūma": "šūtu", "niharraṣa": "harāṣu", "ahīka": "ahu", "tūbil": "wabālu", "ahēya": "ahu", "uqarrāba": "qerēbu", "hiṭṭû": "hīṭu", "ramanšu": "ramānu", "utamme": "tamû", "issarap": "šarāpu", "maṣṣarāti": "maṣṣartu", "urkīe": "arkû", "Til-Barsiba": "Til-Barsip", "iddinanni": "tadānu", "Manṣuate": "Manṣuati", "marʾēšu": "māru", "iqṭarbūni": "qerēbu", "lapṭuršunu": "paṭāru", "lušaṣbissunu": "ṣabātu", "ahhēšunu": "ahu", "parriṣūte": "parriṣu", "duāki": "dâku", "iddubbu": "dabābu", "šakni": "šaknu", "maqarrāt": "maqarratu", "tibni": "tibnu", "ebissu": "ebissu", "appārī": "appāru", "ebissi": "ebissu", "emūqašūni": "emūqu", "Kislimi": "Kislimu", "Dur-Šarruken": "Dur-Šarruken", "qurubu": "qurbu", "qurbat": "qurbu", "udubbiku": "tabāku", "patiat": "patiu", "karrat": "karru", "idabbūbu": "dabābu", "Kutie": "Kute", "Kar-Nergal": "Kar-Nergal", "Mannu-ki-Nergal": "Mannu-ki-Nergal", "ešši": "eššu", "erēni": "erēnu", "assakan": "šakānu", "išme": "šemû", "nuramma": "ramû", "dūku": "dâku", "ussaqalpa": "neqelpû", "patte": "pattu", "qaqqaru": "qaqqaru", "uṣurraššunu": "naṣāru", "armītu": "Armaya", "Ṣurri": "Ṣurru", "lušēbilūši": "wabālu", "ussēbilašše": "wabālu", "Hi-rumu": "Hi-rumu", "ēqu": "ēqu", "ilānišu": "ilu", "lantuh": "matāhu", "ussagliūšu": "galû", "ikkisūni": "nakāsu", "šēpi": "šēpu", "hanīqi": "hanqu", "annūtu": "annû", "ussēṣi": "aṣû", "Immiha": "Immiha", "illakāni": "alāku", "lunammiša": "namāšu", "ariš": "eršu", "ingallīšunu": "niggallu", "ṣīrāni": "ṣīru", "Gargarmesaya": "Gargamesaya", "Marqasaya": "Marqasaya", "Samʾalaya": "Samʾalaya", "Sidudaya": "Asdudaya", "Turbisiba": "Til-Barsip", "ētatqūni": "etēqu", "Kubanaše": "Kubanaše", "iktalʾūšunu": "kalû", "assaparra": "šapāru", "ettiqu": "etēqu", "urtammeu": "ramû", "ētabrūni": "ebēru", "ṣīru": "ṣīru", "šanû": "šanû", "dibbīšunu": "dibbu", "ušebbāla": "wabālu", "unammaša": "namāšu", "lišparūni": "šapāru", "lašme": "šemû", "Matenni": "Metenna", "Danapaya": "Danapaya", "nišši": "našû", "niddinaššu": "tadānu", "abutu": "awātu", "ahīšu": "ahu", "išpurašūni": "šapāru", "maddattu": "maddattu", "dīna": "tadānu", "iddubub": "dabābu", "lussik": "esēhu", "lašpura": "šapāru", "maddatti": "maddattu", "arīši": "eršu", "eqlātišunu": "eqlu", "kirâtišunu": "kirû", "Giri-Baʾal": "Gir-Baʾal", "ētarbūni": "erēbu", "liqbiu": "qabû", "zarʾīšu": "zēru", "tabkušunu": "tabku", "ussallime": "šalāmu", "issanahhiru": "sahāru", "kiṣiršunu": "kiṣru", "QIzalaya": "QIzalayu", "illi": "elû", "haramme": "haramma", "utarru": "târu", "iqābi": "qabû", "dān": "dannu", "dayālī": "dayyālu", "issuhurūni": "sahāru", "ayāka": "ayyaka", "imteṭi": "maṭû", "ša-lišānī": "ša-lišāni", "nakri": "nakru", "turgumāni": "targumannu", "Quwaya": "Quwaya", "ipinnutu": "ipinnutu", "kūdin": "kūdanu", "Kar-Salmanu-ašared": "Kar-Salmanu-ašared", "beʾedu": "bēdu", "illukūni": "alāku", "išpurannāšīni": "šapāru", "iktarru": "karāru", "iqabbûniššu": "qabû", "Hagranu": "Hagaranu", "Hamete": "Hamete", "ahturup": "harāpu", "šaglûni": "šuglû", "ussagli": "galû", "ūdi": "wadû", "Elamaya": "Elamaya", "ussaglišunu": "galû", "igdalû": "galû", "Gaʾamanu": "Gaʾamanu", "ahhēšu": "ahu", "Kummaya": "Kummaya", "ussahhiršunu": "sahāru", "rēhu": "rēhu", "ša-qurribīte": "ša-qurbūti", "habta": "habtu", "Nabu-ahu-iddina": "Nabu-ahu-iddina", "Kudurru": "Kudurru", "pīhatu": "pīhātu", "maškiru": "maškuru", "šalimti": "šalimtu", "apteqidšu": "paqādu", "ittabšû": "bašû", "hīṭīya": "hīṭu", "itâra": "târu", "kaššudāk": "kuššudu", "piltu": "pištu", "iltaknuʾinni": "šakānu", "lušeṣṣīka": "aṣû", "tettiq": "etēqu", "šūtuqu": "etēqu", "habtatu": "habtu", "ušellanni": "elû", "ikarrubu": "karābu", "udarra": "darû", "ṭēnšūni": "ṭēmu", "hurṣa": "harāṣu", "mātīšu": "mātu", "nēhat": "nēhu", "eppušu": "epēšu", "ṣābānīšu": "ṣābu", "ušazzizūni": "izuzzu", "nuzaʾʾizaššunu": "zâzu", "Tardit-Aššur": "Tarditu-Aššur", "uptattišu": "petû", "izzakar": "zakāru", "uzzakki": "zakû", "ittidin": "tadānu", "allikūni": "alāku", "luramme": "ramû", "Tabali": "Tabalu", "lunammiš": "namāšu", "libbašunu": "libbu", "Belu-lu-dari": "Belu-lu-dari", "Ahu-nuri": "Ahu-nuri", "šarrušunu": "šarru", "ahîš": "ahāmiš", "šaʾal": "šâlu", "tillī": "tillu", "iṣṣa": "našû", "abutunni": "awātu", "Mullissu": "Mullissu", "tētelia": "elû", "ētebir": "ebēru", "kirâti": "kirû", "šiprīma": "šipru", "kaprāni": "kapru", "pēthallī": "pēthallu", "Arumu": "Arumu", "Al-Adad": "Al-Adad", "Ša-Uqimutaya": "Ša-Uqimutaya", "assahūru": "sahāru", "iddinūninni": "tadānu", "ukannaš": "kanāšu", "Suhaya": "Suhaya", "emūqīšu": "emūqu", "tardītī": "terdītu", "elēni": "elēnu", "ībirūni": "ebēru", "ahu": "ahu", "šanīta": "šanû", "Bab-bitqa": "Bab-bitqi", "huṣṣēti": "huṣṣutu", "uhtaṣṣiṣu": "haṣāṣu", "ittišunu": "itti", "išqišunu": "isqu", "elēnu": "elēnu", "ṭēma": "ṭēmu", "pānīkunu": "pānu", "ṣālta": "ṣāltu", "deka": "dekû", "iltanapparūniššu": "šapāru", "abkannāšīma": "abāku", "īnaka": "īnu", "dekēma": "dekû", "abkannāši": "abāku", "Dur-Am-iababa": "Dur-Ammi-iababa", "ussēliu": "elû", "issuhra": "sahāru", "iqṭarbāni": "qerēbu", "šina": "šina", "Madaya": "Madaya", "Taʾuzi": "Duʾuzu", "Urzuhina": "Arzuhina", "pēthallāka": "pēthallu", "ammarakku": "namarkû", "ētarāba": "erēbu", "rapšūti": "rapšu", "ipparšidūni": "naparšudu", "ipahhuru": "pahāru", "habtūni": "habtu", "batiqtu": "batiqtu", "niharrāṣa": "harāṣu", "ubbil": "wabālu", "maṣṣarte": "maṣṣartu", "apqidka": "paqādu", "kettû": "kittu", "mugirru": "mugerru", "iktali": "kalû", "paqdu": "paqdu", "īmurū": "amāru", "išmû": "šemû", "limētīya": "liwītu", "sīhu": "sīhu", "īnī": "īnu", "izerrannimma": "zêru", "altemu": "šemû", "akkāʾi": "akkāʾi", "šēpīt": "šēpītu", "aṣbatu": "ṣabātu", "lumašširma": "ašāru", "luṣbat": "ṣabātu", "kittû": "kittu", "maṣû": "maṣû", "idabbubma": "dabābu", "la-qātī": "la-qāt", "ušelli": "elû", "sakkiki": "sukkuku", "umaššaranni": "ašāru", "napšātīya": "napištu", "arrat": "arratu", "ihṭû": "haṭû", "undišširu": "ašāru", "mīti": "mītu", "ṣēri": "ṣēru", "habbātu": "habbātu", "uṣṣûnu": "aṣû", "epinni": "epinnu", "iptalšu": "palāšu", "Dilbataya": "Dilbataya", "kurummatā": "kurummatu", "ebūrišunu": "ebūru", "errišu": "erēšu", "uṣṣi": "aṣû", "ittaši": "našû", "umaššarannimma": "ašāru", "zērē": "zēru", "erriš": "erēšu", "īpušu": "epēšu", "ṭūb": "ṭūbu", "ikkal": "akālu", "Ahi-liya": "Ahu-ilaʾi", "maṣṣarat": "maṣṣartu", "Saggil": "Esaggil", "mādiš": "mādiš", "Ariqu": "Zariqu", "itbû": "tebû", "Hamani": "Hamanu", "lillikūma": "alāku", "imangurūma": "magāru", "tahtabta": "habātu", "ṣillu": "ṣillu", "ihabbatu": "habātu", "ihabbatanni": "habātu", "Iqišaya": "Iqišaya", "tirri": "târu", "Ulmunaši": "Ulmunaši", "piqdātēšu": "piqittu", "bītīšu": "bītu", "ibaššû": "bašû", "unammušu": "namāšu", "eleppātikunu": "eleppu", "huṭṭa": "haṭāṭu", "liqbâššu": "qabû", "eleppātīšu": "eleppu", "lihṭūṭu": "haṭāṭu", "Data": "Data", "Šumu-iddina": "Šumu-iddina", "Mulliltu": "Mulliltu", "liqbaʾ": "qabû", "uṣalla": "ṣullû", "agâ": "agâ", "āmur": "amāru", "balṭātu": "balṭu", "idātīka": "ittu", "miṭēti": "miṭītu", "luramma": "ramû", "lurqud": "raqādu", "Gaga": "Gaga", "mītat": "mītu", "ahūku": "ahu", "dalih": "dalhu", "alkamma": "alāku", "amuršu": "amāru", "altaprakka": "šapāru", "kuldu": "kašādu", "īdaʾ": "wadû", "duluhtīya": "duluhtu", "nipih": "niphu", "taklāka": "taklu", "Šulluma": "Šulluma", "išaʾʾal": "šâlu", "niqṭibaššu": "qabû", "Salame": "Salamu", "liššiu": "našû", "išappar": "šapāru", "Patibiri": "Patibiri", "ūri": "ūru", "Hagaranu": "Hagaranu", "Qarradi": "Qarradi", "nāgirātešunu": "nāgiru", "ussaškinšunu": "šakānu", "tapallah": "palāhu", "ṣīāni": "aṣû", "ālānikunu": "ālu", "šība": "ašābu", "marʾēkunu": "māru", "šarrīni": "šarru", "nušaṣbit": "ṣabātu", "urhu": "arhu", "elli": "elû", "issakanūma": "šakānu", "liškun": "šakānu", "likšūdu": "kašādu", "šunšu": "šumu", "dārâti": "dārītu", "harbānāte": "harbānāti", "usahhar": "sahāru", "Parni-alde": "Parni-alde", "annūte": "annû", "Yadaʾ-la-nibi": "Yadaʾ-la-nibi", "Ṣira": "Ṣira", "ēliūni": "elû", "Yataya": "Yataʾ", "issēribūšunu": "erēbu", "ittannūniššunu": "tadānu", "isharūni": "sahāru", "ēlûni": "elû", "Šubriaye": "Šubriaya", "Parnalde": "Parni-alde", "dāgil": "dāgilu", "iṣṣūrātišu": "iṣṣūru", "lušēbila": "wabālu", "iṣṣūrāti": "iṣṣūru", "uṭâbūni": "ṭiābu", "rabiūtīšu": "rabiu", "tamītu": "tamītu", "Aššur-belu-uṣur": "Aššur-belu-uṣur", "duākīya": "dâku", "lūda": "wadû", "Nabu-išmanni": "Nabu-išmanni", "aṣappi": "aṣappu", "unūtu": "unūtu", "urāt": "urû", "amnu": "manû", "pūtūwa": "pūtu", "ugdatammir": "gamāru", "Ahu-lamur": "Ahu-lamur", "Eluli": "Elulu", "liptu": "liptu", "iltapassu": "lapātu", "urammišu": "ramû", "harammīma": "haramma", "ittaqbi": "qabû", "liqbi": "qabû", "asîni": "asû", "Nergal-belu-udaʾʾan": "Nergal-belu-udaʾʾan", "liṣbat": "ṣabātu", "Marduk-remanni": "Marduk-remanni", "isinnu": "isinnu", "epiš": "epšu", "aladlammî": "aladlammû", "bābāte": "bābu", "aktarar": "karāru", "ibattuqu": "batāqu", "aladlammû": "aladlammû", "batqūte": "batqu", "lapdunni": "lapdunnu", "nišakkan": "šakānu", "dannūtu": "dannu", "bābi": "bābu", "qabassīte": "qabaltīu", "rīmāni": "rīmu", "upâhušunu": "puhhu", "utârušunu": "târu", "qabassīti": "qabaltīu", "kītu": "kittu", "līṭu": "līṭu", "lēṣiru": "eṣēru", "lušēbilūni": "wabālu", "ziqpu": "ziqpu", "Hazzataya": "Hazzataya", "Yaʾuduaya": "Yaʾudaya", "Ban-Ammanaya": "Ban-Ammanaya", "maddanātešunu": "maddattu", "Udumuaya": "Udumaya", "Ašdudaya": "Asdudaya", "Anqarrunaya": "Amqarrunaya", "Zabban": "Zabban", "daiqu": "damqu", "nikarrarūni": "karāru", "ētellû": "elû", "isarruhu": "sarāhu", "nikrūru": "karāru", "bīrāte": "birtu", "Bel-abuʾa": "Bel-abuʾa", "Libbi-ali": "Libbi-ali", "nussākil": "akālu", "irrīšu": "riāšu", "iktarbu": "karābu", "ṣibirāti": "ṣipirtu", "tadinni": "tadnu", "ṣibirtu": "ṣipirtu", "sadrāte": "sadru", "manâya": "manû", "harbite": "harbu", "ammite": "ammiu", "ṭup": "ṭuppu", "dannani": "dannu", "niṣabbat": "ṣabātu", "Urdu-Allaya": "Urdu-Allaya", "iddanakka": "tadānu", "Aššur-šitti-uṣur": "Aššur-šittu-uṣur", "piqtatte": "pīqat", "mūqāya": "emūqu", "ahaṣṣīni": "haṣānu", "akālišunu": "akālu", "isallûni": "salāʾu", "imūta": "mâtu", "gabbišūma": "gabbu", "assaṭāra": "šaṭāru", "erimtu": "erimtu", "Bel-bunaya": "Bel-bunaya", "tašīṭi": "šâṭu", "arki": "arki", "nakkamte": "nakkamtu", "lillûni": "elû", "litruṣu": "tarāṣu", "maqarrutu": "maqarrutu", "masenni": "mašennu", "Ayari": "Ayaru", "maškuru": "maškuru", "ūtalli": "elû", "Aššur-matka-pahhir": "Aššur-matka-pahhir", "ipūgūni": "puāgu", "pānītê": "pānītu", "laqiu": "leqû", "errabiu": "erbû", "nissuqussu": "laqātu", "ilput": "lapātu", "uhtalliqūšu": "halāqu", "ebūrāni": "ebūru", "kalāma": "kalāma", "Mahde": "Mahde", "niddanūni": "tadānu", "šīti": "šīti", "Šabirešu": "Šabirešu", "lillik": "alāku", "ugdammera": "gamāru", "urû": "urû", "ukâlla": "kullu", "isahhurūni": "sahāru", "urātēya": "urû", "urāti": "urû", "nušettaq": "etēqu", "urâya": "urû", "appātīya": "appatu", "Nabuʾa": "Nabuʾa", "ussētiqu": "etēqu", "šēpēya": "šēpu", "qarīte": "qerītu", "luzakki": "zakû", "kaqqaršunu": "qaqqaru", "ukīlūni": "kullu", "iqbâni": "qabû", "Tunaya": "Tunaya", "dullīni": "dullu", "neppaš": "epēšu", "Šarru-ilaʾi": "Šarru-ilaʾi", "tabkī": "tabku", "qāt": "qātu", "ahūka": "ahu", "Bel-eriba": "Bel-eriba", "ša-maṣṣarti": "ša-maṣṣarti", "Issar-šumu-ereš": "Issar-šumu-ereš", "raksu": "raksu", "šēriba": "erēbu", "lahhurru": "mahāru", "Rable": "Rable", "usseribāni": "erēbu", "ēnātīya": "īnu", "untaddid": "madādu", "mešli": "mišlu", "lērub": "erēbu", "mešlumma": "mišlu", "Aini-il": "Eni-il", "ittahar": "mahāru", "mešlimma": "mišlu", "ramenīšunu": "ramānu", "ušēribūni": "erēbu", "qabassi": "qabaltu", "uššurat": "uššuru", "mugirrīya": "mugerru", "ipqidannīni": "paqādu", "laṣṣur": "naṣāru", "tapūga": "puāgu", "eqelšu": "eqlu", "eqlī": "eqlu", "naši": "našû", "šanāti": "šattu", "pāhatūtu": "pīhātūtu", "iptaqdanni": "paqādu", "matimēni": "matimeni", "eqli": "eqlu", "ammie": "ammiu", "ummīdi": "emēdu", "Radanu": "Radanu", "hūl": "hūlu", "Azari": "Azari", "tahūmušunu": "tahūmu", "ūbilannīni": "wabālu", "iptâṣu": "paʾāṣu", "qātātišunu": "qātu", "hurādu": "hurādu", "pîni": "pû", "ētabarūni": "ebēru", "paršamūti": "puršumu", "nagie": "nagû", "assaʾalšunu": "šâlu", "iddinaššūni": "tadānu", "ahhēni": "ahu", "eqelšunu": "eqlu", "rammu": "rammû", "ittūrudu": "arādu", "lūkīnu": "kânu", "šalmūti": "šalmu", "bēlê": "bēlu", "ṣahitūni": "ṣahtu", "ibattaq": "batāqu", "išammēma": "šemû", "ibtaqūni": "batāqu", "eppal": "apālu", "eqlātīya": "eqlu", "kaspê": "kaspu", "nakkamtu": "nakkamtu", "šazzīzi": "izuzzu", "rēssu": "rēšu", "anaššûni": "našû", "Aššur-belu-taqqin": "Aššur-belu-taqqin", "ummânu": "ummiānu", "uballiṭūni": "balāṭu", "šiprānīka": "šipru", "šitappar": "šapāru", "pahhira": "pahāru", "šēbilaššunu": "wabālu", "Ituʾu": "Ituʾaya", "ušettaqūnišanūni": "etēqu", "tūdâ": "wadû", "iškāri": "iškāru", "emādu": "emēdu", "ētarbāni": "erēbu", "šapir": "šapru", "nubutti": "nubattu", "inaṣṣar": "naṣāru", "akannaka": "akannaka", "kūnu": "kūnu", "Rapiša": "Rapiša", "isītāti": "isītu", "uhtarrīdi": "harādu", "azzibil": "zabālu", "atabbak": "tabāku", "Menaga": "Menaga", "harrudanni": "hardu", "uharrāda": "harādu", "azabbil": "zabālu", "ussaṣbit": "ṣabātu", "Aššur-natkil": "Aššur-natkil", "Meṣi": "Meṣi", "ellia": "elû", "iṣabbat": "ṣabātu", "pê": "pû", "battabattušunu": "battubattu", "Atlur": "Atlur", "ilki": "ilku", "rēhāte": "rēhu", "Ukkaya": "Ukkaya", "agdiriššu": "gerû", "ālšu": "ālu", "takaššāda": "kašādu", "ṣāssīya": "ṣāltu", "bīlanni": "wabālu", "battebattūka": "battubattu", "nahhīṣi": "mahāṣu", "amahhāṣa": "mahāṣu", "Issete": "Issete", "šatîšunu": "šatû", "niraṣṣipūni": "raṣāpu", "tarīṣi": "tarṣu", "niraṣṣippi": "raṣāpu", "niškun": "šakānu", "ša-maṣṣarāti": "ša-maṣṣarti", "lēliūni": "elû", "umām": "umāmu", "Samirna": "Samerina", "šadû": "šadû", "šanî": "šanû", "piqitti": "piqittu", "papāhāti": "papāhu", "karānī": "karānu", "gabbušu": "gabbu", "qātīya": "qātu", "ahaṣṣin": "haṣānu", "bubūte": "bubūtu", "kitkittê": "kiškattû", "laddinni": "tadānu", "maṣûni": "maṣû", "Hindaraya": "Hindaraya", "Haṭallaya": "Haṭallaya", "Zer-abi": "Zer-abi", "pirsi": "pirsu", "zizibi": "šizbu", "Šamaš-eriba": "Šamaš-eriba", "Garaba": "Garaba", "Gabbu-Šamaš": "Gabbu-Šamaš", "batūlānišunu": "batūlu", "ṣarrābāte": "ṣarrāpu", "idânu": "ēdû", "ērib": "ēribu", "kinālti": "kiništu", "ašarēdūti": "ašarēdu", "libbakunu": "libbu", "ṭābākunu": "ṭābu", "tašmeāni": "šemû", "palhākunu": "palhu", "hirda": "harādu", "suqāqāte": "sūqāqû", "ṣabbita": "ṣabātu", "ramenīkunu": "ramānu", "uṣra": "naṣāru", "aqṭarbakkunu": "qerēbu", "Naʾdi-ilu": "Naʾdi-ilu", "palhu": "palhu", "igdanarruru": "qarāru", "ūdû": "wadû", "ahhēkunu": "ahu", "ērubanni": "erēbu", "iṭībannīni": "ṭiābu", "hīṭakunu": "hīṭu", "aqarribūni": "qerēbu", "iptaqdu": "paqādu", "ašpuraššūni": "šapāru", "Hulbuna": "Hulbuna", "šaknāku": "šaknu", "isassi": "šasû", "addanūni": "tadānu", "damqāti": "damqu", "lubaʾʾi": "buʾʾû", "iptite": "petû", "ittūṣi": "aṣû", "kammusākunu": "kamsu", "palhušu": "palhu", "nussatammah": "samāhu", "alak": "alāku", "qibaššunu": "qabû", "lūṣûni": "aṣû", "alkāni": "alāku", "libbikunu": "libbu", "lusammeh": "samāhu", "iqṭibaššunu": "qabû", "immaggurūni": "magāru", "issuhūra": "sahāru", "idabbub": "dabābu", "nētamar": "amāru", "nuṣṣâ": "aṣû", "nukalla": "kullu", "nemmarūni": "amāru", "uppušu": "epēšu", "Arumû": "Arumu", "Sapia": "Sapia", "ūṣâni": "aṣû", "Buharru": "Buharru", "ihtabtūni": "habātu", "attakāni": "alāku", "gišimmaru": "gišimmaru", "dūka": "dâku", "širkī": "šerku", "šandabakki": "šandabakku", "qassi": "qaštu", "Armete": "Armitu", "lūbilaššu": "wabālu", "Qurdi-ili-lamur": "Qurdi-ili-lamur", "Yaunaya": "Yaunaya", "Samsimuruna": "Samsimuruna", "Hariṣu": "Hariṣu", "ūtappišu": "epēšu", "attatlak": "alāku", "iššiu": "našû", "ēteliu": "elû", "qabli": "qablu", "tānti": "tiāmtu", "ihtalqu": "halāqu", "Yauna": "Yauna", "ellûni": "elû", "Danabi": "Danabu", "araṣibbi": "raṣāpu", "ēdu": "ēdu", "lušēšībi": "ašābu", "Aqqarrunaya": "Amqarrunaya", "ahtīaṭa": "hiāṭu", "addubub": "dabābu", "ikkārāti": "ikkaru", "Aššur-nirka-uṣur": "Aššur-nirka-uṣur", "zarʾēni": "zēru", "rahiṣ": "rahṣu", "aršu": "eršu", "ītaraš": "erēšu", "maʾʾutte": "maʾʾuttu", "ētaklu": "akālu", "maṣṣartušunu": "maṣṣartu", "ludaʾʾīni": "danānu", "ramanīni": "ramānu", "ēṣidī": "ēṣidu", "maṭi": "maṭû", "ušallam": "šalāmu", "Bit-Eriya": "Bit-Eriya", "aruš": "erēšu", "taktarma": "karāmu", "arraš": "erēšu", "simin": "simānu", "uqarrab": "qerēbu", "emūqāyāni": "emūqu", "Nahiši": "Nahiši", "ussēṣišu": "aṣû", "namaddāti": "namaddu", "dalāti": "daltu", "uṣṣabbīti": "ṣabātu", "taltukūni": "latāku", "ittannūnikâ": "tadānu", "Digirina": "Digirina", "altukūni": "latāku", "addinūni": "tadānu", "allakanni": "alāku", "kaqqiri": "qaqqaru", "idunni": "idu", "ittannanāši": "tadānu", "šumīka": "šumu", "lidibub": "dabābu", "riṣipti": "riṣiptu", "unīni": "umnīnu", "riṣiptu": "riṣiptu", "riṣībi": "raṣāpu", "unīnê": "umnīnu", "araṣṣībi": "raṣāpu", "ētamur": "amāru", "ṣinda": "ṣamādu", "rammea": "ramû", "danniš": "danniš", "qirsī": "qirsu", "dun": "dunnu", "mahhīri": "mahāru", "ṣabbira": "ṣabāru", "issēka": "išti", "muthu": "matāhu", "nāšiāni": "nāšiu", "tamattah": "matāhu", "amattah": "matāhu", "Gilu": "Gilu", "uktabbir": "kabāru", "Iqipi": "Iqipi", "sukkalli": "šukkallu", "rabî": "rabû", "mušāqir": "mušēqiru", "dulluša": "dullu", "aškunamma": "šakānu", "šurkī": "šerku", "Kutea": "Kute", "ṣillīnu": "ṣillu", "iqtirbūna": "qerēbu", "tāmuru": "amāru", "elâ": "elû", "mātāti": "mātu", "ramnā": "ramānu", "dunqīya": "dumqu", "banītīya": "banītu", "Nabu-leʾi": "Nabu-leʾi", "ludbubma": "dabābu", "dibbīya": "dibbu", "lilqâmma": "leqû", "tūrti": "tūrtu", "išakkanu": "šakānu", "iqabbâ": "qabû", "lūpuš": "epēšu", "Ahu-damqi": "Ahu-damqi", "našparti": "našpartu", "ṭuppīšu": "ṭuppu", "ṭēnšu": "ṭēmu", "Turmuna": "Turmuna", "kabsat": "kabsu", "erruš": "erēšu", "ūrī": "ūru", "nizzazāma": "izuzzu", "ittaškin": "šakānu", "rāšiʾu": "rāšû", "nāgiri": "nāgiru", "Ameli": "Ameli", "Bel-ereš": "Bel-ereš", "ašparūni": "šapāru", "Atamar-Aššur": "Atamar-Aššur", "ammūti": "ammiu", "Nabu-killanni": "Nabu-killanni", "mēni": "mīnu", "Sin-šabši": "Sin-šabši", "qarbātīya": "qarbāte", "ēkal": "ēkallu", "māšarti": "māšartu", "dēnī": "dīnu", "Hindanaya": "Hindanaya", "ussēbiraššunu": "ebēru", "ēbirūni": "ebēru", "rēši": "rēšu", "inaṣṣur": "naṣāru", "mēru": "mīru", "Hindani": "Hindanu", "lurammiu": "ramû", "išammûni": "šemû", "hīṭāya": "hīṭu", "lidūkanni": "dâku", "idukkūni": "dâku", "issaknanni": "šakānu", "kayamānūte": "kayyamānu", "muhūru": "mahāru", "Dadi": "Dadi", "dīni": "tadānu", "Kisasi": "Kisasi", "maddaʾtu": "maddattu", "tašlīšīya": "tašlīšu", "ašapraššu": "šapāru", "šībi": "ašābu", "nihhūru": "mahāru", "lūšībi": "ašābu", "tayārte": "tayyartu", "alaqqut": "laqātu", "amahhāra": "mahāru", "imarraṣaššu": "marāṣu", "ilaqqut": "laqātu", "erši": "eršu", "izabbilūšu": "zabālu", "mārīšu": "māru", "imahhuru": "mahāru", "ṣabta": "ṣabātu", "tamaqquta": "maqātu", "maddaʾti": "maddattu", "lašʾāla": "šâlu", "ihturūpu": "harāpu", "ēnu": "īnu", "ēni": "īnu", "nidabbūbu": "dabābu", "damqūte": "damqu", "amahharūni": "mahāru", "ikkir": "nakāru", "qaʾʾi": "qinû", "šarrimma": "šarru", "imahhar": "mahāru", "kabbissu": "kabātu", "ilīya": "ilu", "ukabbadušūni": "kabātu", "libbaka": "libbu", "ṭābka": "ṭābu", "taddanūni": "tadānu", "biltāya": "biltu", "balaṭṭu": "balāṭu", "isqāte": "isqu", "rabrabānī": "rabrabānī", "imaṭṭiūni": "maṭû", "izirranni": "zêru", "šapputu": "šappatu", "emmadūni": "emēdu", "niraṣṣip": "raṣāpu", "nugdammer": "gamāru", "hanšê": "hamšā", "ihtalqa": "halāqu", "ēteli": "elû", "lēlû": "elû", "addanaššu": "tadānu", "rēhat": "rēhu", "lušēbilu": "wabālu", "ṭupšarri": "ṭupšarru", "šaddu": "šaddu", "issapruniššu": "šapāru", "saddu": "šaddu", "išparūni": "šapāru", "iktanku": "kanāku", "rēhūti": "rēhtu", "ittatku": "alāku", "hiṣin": "haṣānu", "iyû": "yāʾu", "piqittu": "piqittu", "maʾdu": "mādu", "attanahhar": "mahāru", "šammīya": "šammu", "Gilgime": "Gilgime", "Kunane": "Kunane", "pargāni": "pargānu", "Bel-Harran-šarru-uṣur": "Bel-Harran-šarru-uṣur", "Ilanasa": "Ilanasa", "Urmu": "Urmu", "anūte": "unūtu", "Attar-idri": "Attar-idri", "rēʾê": "rēʾû", "lihṣinu": "haṣānu", "ibtēru": "bêru", "issaknu": "šakānu", "šalhīe": "šalhû", "iharruṣu": "harāṣu", "ammūte": "ammiu", "Qurru": "Gurraya", "šihiṭ": "šehṭu", "killu": "ikkillu", "ittaškan": "šakānu", "nirtidipšunu": "radāpu", "Reš-ṣurri": "Reš-ṣurri", "niṣṣabta": "ṣabātu", "šalhīu": "šalhû", "nēmur": "amāru", "hirīṣi": "harīṣu", "batqu": "batqu", "Bibie": "Bibi", "Hunaba": "Hunaba", "Ištahup": "Ištahup", "naṣūniššu": "našû", "assaʾalšu": "šâlu", "Gimir": "Gimir", "irûbu": "râbu", "iqullu": "qâlu", "uṣê": "aṣû", "Mannaya": "Manna", "Yaʾudaya": "Yaʾudaya", "gušūrī": "gušūru", "dannūte": "dannu", "Raṣappa": "Raṣappa", "Adia": "Adia", "akanna": "akanna", "bīti": "bītu", "urrudūni": "arādu", "iqbia": "qabû", "ušazibilūni": "zabālu", "šaṣbissunu": "ṣabātu", "eṣidīssunu": "eṣidītu", "sāgu": "sāgu", "hintu": "himtu", "mašennu": "mešēnu", "imārīya": "imēru", "maṣin": "maṣû", "qirsīyāma": "qirsu", "lamtuh": "matāhu", "Nupari": "Nupari", "parriṣu": "parriṣu", "nušallim": "šalāmu", "gušūri": "gušūru", "gušūru": "gušūru", "qātātu": "qātu", "Ekallate": "Ekallati", "anūtu": "unūtu", "karaphī": "karaphu", "mahhāṣa": "mahāṣu", "puʾē": "pû", "nakkīsi": "nakāsu", "mahṣu": "mahṣu", "naksu": "naksu", "kuraggī": "kurangu", "ītaṣadu": "eṣēdu", "Ṣabu-damqu": "Ṣabu-damqu", "Arsazaya": "Arsazaya", "šārāni": "šāru", "igāru": "igāru", "libittu": "libittu", "birtuššina": "birti", "qaribtu": "qerbu", "ammatāya": "ammatu", "karru": "karru", "ussēšebišu": "ašābu", "annāte": "annû", "ēnāti": "īnu", "habilte": "hablu", "arrašunu": "arnu", "šībūte": "šību", "ittamû": "tamû", "ašapparūma": "šapāru", "akul": "akālu", "šāšunu": "šâšunu", "mahrīti": "mahrû", "ušēbilamma": "wabālu", "amharaš": "mahāru", "šumāti": "šumu", "šaṭru": "šaṭru", "numissi": "wussû", "kannû": "kīnu", "ašpura": "šapāru", "ittannu": "nadānu", "lihalliqu": "halāqu", "Aššur-šarru-uṣur": "Aššur-šarru-uṣur", "tašpuranni": "šapāru", "Meta": "Meta", "Muskaya": "Muskaya", "Urik": "Urik", "šaprūte": "šapru", "tariṣ": "tarṣu", "ilānīya": "ilu", "qarābi": "qarābu", "salmīni": "salmu", "balāt": "balāt", "ibbattaq": "batāqu", "šupraššu": "šapāru", "šimi": "šemû", "arîqanni": "riāqu", "lušēbilaššû": "wabālu", "šēbilaššu": "wabālu", "libbušu": "libbu", "ippaššar": "pašāru", "assappar": "šapāru", "ihtudu": "hadû", "pānīkāni": "pānu", "takalla": "kalû", "šēbil": "wabālu", "ussēbilakka": "wabālu", "Urpalaʾa": "Urpalaʾa", "hannūti": "annû", "ziqnīšunu": "ziqnu", "mašennaka": "mešēnu", "lušakkilu": "šakkulu", "Kilar": "Kilar", "nagiāni": "nagû", "ētaršanni": "erēšu", "tattidin": "tadānu", "mihrikâ": "mehru", "attamma": "atta", "tuppaš": "epēšu", "qibaššu": "qabû", "palhāka": "palhu", "issilim": "salāmu", "kusāpīka": "kusāpu", "mêka": "mû", "šiti": "šatû", "nikittaka": "niqittu", "Atunnaya": "Atunnaya", "Istuandaya": "Istuandaya", "Bit-Paruta": "Bit-Purutaš", "ipūgušūni": "puāgu", "iktiʾīdi": "kaʾādu", "nāka": "annaka", "māka": "ammaka", "tumazzaʾšunu": "mazāʾu", "ebihka": "ebīhu", "tarakkas": "rakāsu", "hannītu": "annû", "šēpēka": "šēpu", "tattakbas": "kabāsu", "dūlu": "dâlu", "dullakāni": "dullu", "arku": "arku", "butūqu": "batāqu", "kuriu": "kurû", "lērik": "arāku", "addanakkanni": "tadānu", "dibbīšu": "dibbu", "kannušu": "kannušu", "lušabalkita": "nabalkutu", "lušēšibšunu": "ašābu", "šāšu": "šâšu", "tašlīšaka": "tašlīšu", "kallie": "kallû", "lintuhaššu": "matāhu", "laškunšu": "šakānu", "hannāka": "annaka", "usahharūni": "sahāru", "bētīšu": "bītu", "lūbilaššunu": "wabālu", "mar-Barsip": "mar-Barsip", "Kišaya": "Kišaya", "Urukaya": "Urukaya", "Deraya": "Deraya", "šunūni": "šunu", "ūtassīki": "esēhu", "Simani": "Simanu", "uttammišu": "namāšu", "ittatakku": "alāku", "dīnaššu": "tadānu", "attūṣia": "aṣû", "Renni": "Renni", "iṣbatūni": "ṣabātu", "ūmāte": "ūmu", "ašalla": "šâlu", "ušašma": "šemû", "Bessunu": "Bessunu", "ēmidūšanūni": "emēdu", "biltu": "biltu", "pappardalî": "pappardaliu", "attedin": "tadānu", "manêma": "manû", "Mannu-ki-Aššur-leʾi": "Mannu-ki-Aššur-leʾi", "muṭê": "muṭû", "Riba-ahhe": "Riba-ahhe", "Labasi": "Labasi", "Harbiṣaṣu": "Harbiṣaṣu", "ētemidsunu": "emēdu", "ša-maʾāssu": "ša-maʾāssi", "ukâllūni": "kullu", "šaṭir": "šaṭru", "kabar": "kapru", "anāqāti": "anāqutu", "lidnūni": "tadānu", "upahhirūni": "pahāru", "šapluššu": "šaplu", "larkus": "rakāsu", "liškunnūniššunu": "šakānu", "Ilaʾi-Bel": "Ilaʾi-Bel", "Hazala": "Hazala", "kutallašunu": "kutallu", "Harranu": "Harranu", "Til": "Tille", "iṣṣūru": "iṣṣūru", "lû": "lû", "nūnu": "nūnu", "šikārī": "šikaru", "tuhnu": "duhnu", "šūmu": "šūmū", "kaṣip": "kaṣpu", "urhāni": "arhu", "šanīti": "šanû", "išahhuṭu": "šahāṭu", "libitti": "libittu", "ṣindi": "ṣimdu", "ammat": "ammatu", "maqarrattu": "maqarratu", "qanê": "qanû", "kiriʾi": "kirû", "turtān": "tartānu", "Šininahaya": "Šininahaya", "Tasi": "Tasi", "ramenīšu": "ramānu", "Marduk-iddina": "Marduk-iddina", "tahūmekunu": "tahūmu", "battebattekunu": "battubattu", "kēnūni": "kīnu", "ētamrūma": "amāru", "iqabbiu": "qabû", "imuttūma": "mâtu", "asseme": "šemû", "ūṣiūma": "aṣû", "ilkašunu": "ilku", "karme": "karmu", "batqī": "batqu", "hapi": "hepû", "šalmūni": "šalmu", "annūtēma": "annû", "udēya": "udī-", "iktarrūni": "karāru", "ilakšunu": "ilku", "naṣu": "našû", "sissêni": "sisû", "uqarribūni": "qerēbu", "inaššiu": "našû", "Bit-Hamban": "Bit-Hamban", "habbatūni": "habtu", "lēmur": "amāru", "Erimziqi": "Erimziqu", "daʾna": "dannu", "Apinunu": "Apinunu", "baršamūtu": "puršumu", "adabbūbu": "dabābu", "Erimziqaya": "Erimziqaya", "Bir-Bariaš": "Bir-Bariaš", "Apinunaya": "Apinunaya", "ābukūni": "abāku", "Dur-ayumma": "Dur-ayumma", "iduššu": "idu", "Ṣallaya": "Ṣallaya", "Babe-šumki": "Babe-šumki", "Waru": "Waru", "maqtūte": "maqtu", "sissêka": "sisû", "dilip": "dalāpu", "harpu": "harpu", "barûte": "berû", "Durtuni": "Durtunu", "iddinu": "tadānu", "laqqiu": "leqû", "issēte": "ištēn", "namarkû": "namarkû", "Bel-ilaʾi": "Bel-ilaʾi", "atānāti": "atānu", "Bet-Ilaya": "Bet-Ilaya", "Nabu-ušebši": "Nabu-ušebši", "Salamu": "Salamu", "issēya": "išti", "ussētiqūni": "etēqu", "aharrāṣa": "harāṣu", "Inurta-aplu-iddina": "Inurta-aplu-iddina", "ipqiddi": "paqādu", "tašpur": "šapāru", "assakanšu": "šakānu", "attanšu": "tadānu", "ittatakka": "alāku", "Aya-niri": "Aya-nuri", "imtatha": "matāhu", "iktarar": "karāru", "amtahar": "mahāru", "Attar-šumki": "Attar-šumki", "Matiʾ-il": "Matiʾ-il", "šapti": "šaptu", "aktarranni": "karāru", "lihhaṣanni": "mahāṣu", "šēbiranni": "ebēru", "ilkīni": "ilku", "piqitte": "piqittu", "eleppāte": "eleppu", "ittalkāni": "alāku", "tuqarrab": "qerēbu", "Nabu-šarru-uṣur": "Nabu-šarru-uṣur", "Gurali": "Gurali", "Adasi": "Adasi", "iqbiūni": "qabû", "battēšu": "battu", "aqṭibiaššu": "qabû", "issēniu": "ištēnû", "pati": "patiu", "lurammû": "ramû", "Nabu-uṣalla": "Nabu-uṣalla", "Abi": "Abu", "Sarduriana": "Sarduriani", "šuhūṭu": "šahāṭu", "rāme": "ramû", "piqiddi": "paqādu", "liṣṣūru": "naṣāru", "Elizki": "Elizki", "šuhṭa": "šahāṭu", "Sarduriani": "Sarduriani", "liqbâkkunu": "qabû", "Elizkun": "Elizki", "diʾpa": "daʾāpu", "kattemaššunu": "katāmu", "ētamru": "amāru", "emūqīšunu": "emūqu", "pūtūni": "pūtu", "Arṣua": "Arṣua", "ursūtu": "ursūtu", "errabāni": "erēbu", "šanṣura": "šanṣuru", "alāki": "alāku", "etinnāni": "itinnu", "issuhru": "sahāru", "ūmēšu": "ūmu", "ša-arīte": "ša-arīti"}
